{
  "projects": [
    {
      "id": 1,
      "title": "Project 1",
      "erpid": "15001",
      "dept": "M",
      "div": "MP",
      "pjm": "MP",
      "manager": "Donald Duck",
      "sponsor": "Yosimite Sam",
      "md": "Y",
      "pstart": "",
      "pfinish": "",
      "astart": "",
      "afinish": ""
    },
    {
      "id": 2,
      "title": "Project 3",
      "erpid": "15002",
      "dept": "M",
      "div": "MZ",
      "pjm": "MZ",
      "manager": "Mickey Mouse",
      "sponsor": "Roger Rabbit",
      "md": "Y",
      "pstart": "",
      "pfinish": "",
      "astart": "",
      "afinish": ""
    },
    {
      "id": 3,
      "title": "Project 17",
      "erpid": "15003",
      "dept": "M",
      "div": "MP",
      "pjm": "MP",
      "manager": "Goofy",
      "sponsor": "Tom and Jerry",
      "md": "Y",
      "pstart": "",
      "pfinish": "",
      "astart": "",
      "afinish": ""
    },
    {
      "id": 11,
      "title": "Project 1",
      "erpid": "16001",
      "dept": "M",
      "div": "MP",
      "pjm": "MP",
      "manager": "Donald Duck",
      "sponsor": "Yosimite Sam",
      "md": "Y",
      "pstart": "",
      "pfinish": "",
      "astart": "",
      "afinish": ""
    },
    {
      "id": 12,
      "title": "Project 3",
      "erpid": "16002",
      "dept": "M",
      "div": "MZ",
      "pjm": "MZ",
      "manager": "Mickey Mouse",
      "sponsor": "Roger Rabbit",
      "md": "Y",
      "pstart": "",
      "pfinish": "",
      "astart": "",
      "afinish": ""
    },
    {
      "id": 13,
      "title": "Project 17",
      "erpid": "16003",
      "dept": "M",
      "div": "MP",
      "pjm": "MP",
      "manager": "Goofy",
      "sponsor": "Tom and Jerry",
      "md": "Y",
      "pstart": "",
      "pfinish": "",
      "astart": "",
      "afinish": ""
    },
    {
      "id": 21,
      "title": "Project 1",
      "erpid": "17001",
      "dept": "M",
      "div": "MP",
      "pjm": "MP",
      "manager": "Donald Duck",
      "sponsor": "Yosimite Sam",
      "md": "Y",
      "pstart": "",
      "pfinish": "",
      "astart": "",
      "afinish": ""
    },
    {
      "id": 22,
      "title": "Project 3",
      "erpid": "17002",
      "dept": "M",
      "div": "MZ",
      "pjm": "MZ",
      "manager": "Mickey Mouse",
      "sponsor": "Roger Rabbit",
      "md": "Y",
      "pstart": "",
      "pfinish": "",
      "astart": "",
      "afinish": ""
    },
    {
      "id": 23,
      "title": "Project 17",
      "erpid": "17003",
      "dept": "M",
      "div": "MP",
      "pjm": "MP",
      "manager": "Goofy",
      "sponsor": "Tom and Jerry",
      "md": "Y",
      "pstart": "",
      "pfinish": "",
      "astart": "",
      "afinish": ""
    },
    {
      "id": 31,
      "title": "Project 1",
      "erpid": "18001",
      "dept": "M",
      "div": "MP",
      "pjm": "MP",
      "manager": "Daffy Duck",
      "md": "Y",
      "pstart": "",
      "pfinish": "",
      "astart": "",
      "afinish": ""
    },
    {
      "id": 32,
      "title": "Project 3",
      "erpid": "18002",
      "dept": "M",
      "div": "MZ",
      "pjm": "MZ",
      "manager": "Mickey Mouse",
      "sponsor": "Roger Rabbit",
      "md": "Y",
      "pstart": "",
      "pfinish": "",
      "astart": "",
      "afinish": ""
    },
    {
      "id": 33,
      "title": "Project 17",
      "erpid": "18003",
      "dept": "M",
      "div": "MP",
      "pjm": "MP",
      "manager": "Goofy",
      "sponsor": "Tom and Jerry",
      "md": "Y",
      "pstart": "",
      "pfinish": "",
      "astart": "",
      "afinish": ""
    },
    {
      "id": 41,
      "title": "Project 1",
      "erpid": "19001",
      "dept": "M",
      "div": "MP",
      "pjm": "MP",
      "manager": "Donald Duck",
      "sponsor": "Yosimite Sam",
      "md": "Y",
      "pstart": "",
      "pfinish": "",
      "astart": "",
      "afinish": ""
    },
    {
      "id": 42,
      "title": "Project 3",
      "erpid": "19002",
      "dept": "M",
      "div": "MZ",
      "pjm": "MZ",
      "manager": "Minnie Mouse",
      "sponsor": "Tom and Jerry",
      "md": "Y",
      "pstart": "",
      "pfinish": "",
      "astart": "",
      "afinish": ""
    },
    {
      "id": 43,
      "title": "Project 17",
      "erpid": "19003",
      "dept": "M",
      "div": "MP",
      "pjm": "MP",
      "manager": "Goofy",
      "sponsor": "Tom and Jerry",
      "md": "Y",
      "pstart": "",
      "pfinish": "",
      "astart": "",
      "afinish": ""
    },
    {
      "id": 51,
      "title": "Project 1",
      "erpid": "20001",
      "dept": "M",
      "div": "MP",
      "pjm": "MP",
      "manager": "Donald Duck",
      "sponsor": "Yosimite Sam",
      "md": "Y",
      "pstart": "",
      "pfinish": "",
      "astart": "",
      "afinish": ""
    },
    {
      "id": 52,
      "title": "Project 3",
      "erpid": "20002",
      "dept": "M",
      "div": "MZ",
      "pjm": "MZ",
      "manager": "Mickey Mouse",
      "sponsor": "Roger Rabbit",
      "md": "Y",
      "pstart": "",
      "pfinish": "",
      "astart": "",
      "afinish": ""
    },
    {
      "id": 53,
      "title": "Project 17",
      "erpid": "20003",
      "dept": "M",
      "div": "MP",
      "pjm": "MP",
      "manager": "Goofy",
      "sponsor": "Tom and Jerry",
      "md": "Y",
      "pstart": "",
      "pfinish": "",
      "astart": "",
      "afinish": ""
    },
    {
      "id": 61,
      "title": "Project 1",
      "erpid": "21001",
      "dept": "M",
      "div": "MP",
      "pjm": "MP",
      "manager": "Donald Duck",
      "sponsor": "Yosimite Sam",
      "md": "Y",
      "pstart": "",
      "pfinish": "",
      "astart": "",
      "afinish": ""
    },
    {
      "id": 62,
      "title": "Project 3",
      "erpid": "21002",
      "dept": "M",
      "div": "MZ",
      "pjm": "MZ",
      "manager": "Mickey Mouse",
      "sponsor": "Roger Rabbit",
      "md": "Y",
      "pstart": "",
      "pfinish": "",
      "astart": "",
      "afinish": ""
    },
    {
      "id": 63,
      "title": "Project 17",
      "erpid": "21003",
      "dept": "M",
      "div": "MP",
      "pjm": "MP",
      "manager": "Bugs Bunny",
      "sponsor": "Tom and Jerry",
      "md": "Y",
      "pstart": "",
      "pfinish": "",
      "astart": "",
      "afinish": ""
    }
  ],
  "milestones": [
    {
      "id": 1,
      "index": 0,
      "erpid": "19001",
      "guid": "ABCDEF00-1234-4321-ABCD-ABCDEF000001",
      "order": 2,
      "cp": "",
      "cd": "",
      "title": "Milestone A",
      "delid": "",
      "FY": "2019",
      "mdps": "5/5/2019",
      "mdpf": "5/31/2019",
      "mdas": "5/5/2019",
      "mdaf": "5/25/2019",
      "pcomp": 0,
      "pqty": 100,
      "oqty": 70,
      "units": "Drums",
      "status": "Finished On-time",
      "rcc": "",
      "rc": "",
      "phase": "",
      "category": "",
      "leadwc": "",
      "duration": 26,
      "comms": "",
      "uri": "http://localhost:3000/milestones/1"
    },
    {
      "id": 2,
      "index": 1,
      "erpid": "19001",
      "guid": "ABCDEF00-1234-4321-ABCD-ABCDEF000002",
      "order": 1,
      "cp": "",
      "cd": "",
      "title": "Milestone F",
      "delid": "",
      "FY": "2019",
      "mdps": "5/5/2019",
      "mdpf": "5/31/2019",
      "mdas": "5/5/2019",
      "mdaf": "6/25/2019",
      "pcomp": 0,
      "pqty": 10,
      "oqty": 8,
      "units": "Gallons",
      "status": "Finished Late",
      "rcc": "",
      "rc": "",
      "phase": "",
      "category": "",
      "leadwc": "",
      "duration": 26,
      "comms": "",
      "uri": "http://localhost:3000/milestones/2"
    },
    {
      "id": 3,
      "index": 3,
      "erpid": "19001",
      "guid": "ABCDEF00-1234-4321-ABCD-ABCDEF000003",
      "order": 5,
      "cp": "",
      "cd": "",
      "title": "Milestone J",
      "delid": "",
      "FY": "2019",
      "mdps": "4/1/2019",
      "mdpf": "6/6/2019",
      "mdas": "4/5/2019",
      "mdaf": "",
      "pcomp": 0,
      "pqty": 200,
      "oqty": 100,
      "units": "Boxes",
      "status": "Projecting Late",
      "rcc": "",
      "rc": "",
      "phase": "",
      "category": "",
      "leadwc": "",
      "duration": 66,
      "comms": "",
      "uri": "http://localhost:3000/milestones/3"
    },
    {
      "id": 4,
      "index": 2,
      "erpid": "19002",
      "guid": "ABCDEF00-1234-4321-ABCD-ABCDEF000004",
      "order": 4,
      "cp": "",
      "cd": "",
      "title": "Milestone YY",
      "delid": "",
      "FY": "2019",
      "mdps": "1/5/2019",
      "mdpf": "1/31/2019",
      "mdas": "3/5/2019",
      "mdaf": "5/10/2019",
      "pcomp": 0,
      "pqty": 66,
      "oqty": 56,
      "units": "Gallons",
      "status": "Finished Late",
      "rcc": "",
      "rc": "",
      "phase": "",
      "category": "",
      "leadwc": "",
      "duration": 26,
      "comms": "",
      "uri": "http://localhost:3000/milestones/4"
    },
    {
      "id": 5,
      "index": 4,
      "erpid": "19002",
      "guid": "ABCDEF00-1234-4321-ABCD-ABCDEF000005",
      "order": 3,
      "cp": "",
      "cd": "",
      "title": "Milestone T",
      "delid": "",
      "FY": "2019",
      "mdps": "7/5/2019",
      "mdpf": "7/31/2019",
      "mdas": "5/17/2019",
      "mdaf": "7/11/2019",
      "pcomp": 0,
      "pqty": 50,
      "oqty": 25,
      "units": "Units",
      "status": "Finished On-time",
      "rcc": "",
      "rc": "",
      "phase": "",
      "category": "",
      "leadwc": "",
      "duration": 26,
      "comms": "",
      "uri": "http://localhost:3000/milestones/5"
    },
    {
      "id": 6,
      "index": 0,
      "erpid": "19002",
      "guid": "ABCDEF00-1234-4321-ABCD-ABCDEF000006",
      "order": 17,
      "cp": "",
      "cd": "",
      "title": "Milestone Q",
      "delid": "",
      "FY": "2019",
      "mdps": "5/5/2019",
      "mdpf": "5/31/2019",
      "mdas": "5/5/2019",
      "mdaf": "5/25/2019",
      "pcomp": 0,
      "pqty": 0,
      "oqty": 0,
      "units": "Gallons",
      "status": "Finished On-time",
      "rcc": "",
      "rc": "",
      "phase": "",
      "category": "",
      "leadwc": "",
      "comms": "",
      "duration": 26,
      "delete": "N",
      "uri": "http://localhost:3000/milestones/6"
    },
    {
      "id": 7,
      "index": 2,
      "erpid": "19002",
      "guid": "ABCDEF00-1234-4321-ABCD-ABCDEF000007",
      "order": 4,
      "cp": "",
      "cd": "",
      "title": "Milestone YY",
      "delid": "",
      "FY": "2019",
      "mdps": "1/5/2019",
      "mdpf": "1/31/2019",
      "mdas": "3/5/2019",
      "mdaf": "5/10/2019",
      "pcomp": 0,
      "pqty": 0,
      "oqty": 0,
      "units": "Gallons",
      "status": "Finished Late",
      "rcc": "",
      "rc": "",
      "phase": "",
      "category": "",
      "leadwc": "",
      "comms": "",
      "duration": 26,
      "delete": "N",
      "uri": "http://localhost:3000/milestones/7"
    },
    {
      "id": 8,
      "index": 0,
      "erpid": "19003",
      "guid": "ABCDEF00-1234-4321-ABCD-ABCDEF000008",
      "order": 17,
      "cp": "",
      "cd": "",
      "title": "Milestone Q",
      "delid": "",
      "FY": "2019",
      "mdps": "5/5/2019",
      "mdpf": "5/31/2019",
      "mdas": "5/5/2019",
      "mdaf": "5/25/2019",
      "pcomp": 0,
      "pqty": 0,
      "oqty": 0,
      "units": "Gallons",
      "status": "Finished On-time",
      "rcc": "",
      "rc": "",
      "phase": "",
      "category": "",
      "leadwc": "",
      "comms": "",
      "duration": 26,
      "delete": "N",
      "uri": "http://localhost:3000/milestones/8"
    },
    {
      "id": 9,
      "index": 2,
      "erpid": "19003",
      "guid": "ABCDEF00-1234-4321-ABCD-ABCDEF000009",
      "order": 4,
      "cp": "",
      "cd": "",
      "title": "Milestone YY",
      "delid": "",
      "FY": "2019",
      "mdps": "1/5/2019",
      "mdpf": "1/31/2019",
      "mdas": "3/5/2019",
      "mdaf": "5/10/2019",
      "pcomp": 0,
      "pqty": 0,
      "oqty": 0,
      "units": "Gallons",
      "status": "Finished Late",
      "rcc": "",
      "rc": "",
      "phase": "",
      "category": "",
      "leadwc": "",
      "comms": "",
      "duration": 26,
      "delete": "N",
      "uri": "http://localhost:3000/milestones/9"
    },
    {
      "id": 100,
      "index": 0,
      "erpid": "15001",
      "guid": "ABCDEF00-1234-4321-ABCD-ABCDEF000100",
      "order": 2,
      "cp": "",
      "cd": "",
      "title": "Milestone A",
      "delid": "",
      "FY": "2015",
      "mdps": "5/5/2015",
      "mdpf": "5/31/2015",
      "mdas": "5/4/2015",
      "mdaf": "5/25/2015",
      "pcomp": 0,
      "pqty": 100,
      "oqty": 70,
      "units": "Drums",
      "status": "Finished On-time",
      "rcc": "",
      "rc": "",
      "phase": "",
      "category": "",
      "leadwc": "",
      "duration": 26,
      "comms": "",
      "uri": "http://localhost:3000/milestones/100"
    },
    {
      "id": 101,
      "index": 1,
      "erpid": "15001",
      "guid": "ABCDEF00-1234-4321-ABCD-ABCDEF000101",
      "order": 1,
      "cp": "",
      "cd": "",
      "title": "Milestone F",
      "delid": "",
      "FY": "2015",
      "mdps": "2/2/2015",
      "mdpf": "3/31/2015",
      "mdas": "2/5/2015",
      "mdaf": "4/4/2015",
      "pcomp": 0,
      "pqty": 10,
      "oqty": 8,
      "units": "Gallons",
      "status": "Finished Late",
      "rcc": "",
      "rc": "",
      "phase": "",
      "category": "",
      "leadwc": "",
      "duration": 26,
      "comms": "",
      "uri": "http://localhost:3000/milestones/101"
    },
    {
      "id": 102,
      "index": 3,
      "erpid": "15001",
      "guid": "ABCDEF00-1234-4321-ABCD-ABCDEF000102",
      "order": 5,
      "cp": "",
      "cd": "",
      "title": "Milestone J",
      "delid": "",
      "FY": "2015",
      "mdps": "8/1/2015",
      "mdpf": "9/6/2015",
      "mdas": "8/5/2015",
      "mdaf": "",
      "pcomp": 0,
      "pqty": 200,
      "oqty": 100,
      "units": "Boxes",
      "status": "Projecting Late",
      "rcc": "",
      "rc": "",
      "phase": "",
      "category": "",
      "leadwc": "",
      "duration": 66,
      "comms": "",
      "uri": "http://localhost:3000/milestones/102"
    },
    {
      "id": 103,
      "index": 2,
      "erpid": "15002",
      "guid": "ABCDEF00-1234-4321-ABCD-ABCDEF000103",
      "order": 4,
      "cp": "",
      "cd": "",
      "title": "Milestone YY",
      "delid": "",
      "FY": "2015",
      "mdps": "1/5/2015",
      "mdpf": "2/14/2015",
      "mdas": "1/5/2015",
      "mdaf": "3/10/2015",
      "pcomp": 0,
      "pqty": 66,
      "oqty": 56,
      "units": "Gallons",
      "status": "Finished Late",
      "rcc": "",
      "rc": "",
      "phase": "",
      "category": "",
      "leadwc": "",
      "duration": 26,
      "comms": "",
      "uri": "http://localhost:3000/milestones/103"
    },
    {
      "id": 104,
      "index": 4,
      "erpid": "15002",
      "guid": "ABCDEF00-1234-4321-ABCD-ABCDEF000104",
      "order": 3,
      "cp": "",
      "cd": "",
      "title": "Milestone TT",
      "delid": "",
      "FY": "2015",
      "mdps": "7/5/2015",
      "mdpf": "7/31/2015",
      "mdas": "5/17/2015",
      "mdaf": "7/7/2015",
      "pcomp": 0,
      "pqty": 50,
      "oqty": 25,
      "units": "Units",
      "status": "Finished On-time",
      "rcc": "",
      "rc": "",
      "phase": "",
      "category": "",
      "leadwc": "",
      "duration": 26,
      "comms": "",
      "uri": "http://localhost:3000/milestones/104"
    },
    {
      "id": 105,
      "index": 0,
      "erpid": "15003",
      "guid": "ABCDEF00-1234-4321-ABCD-ABCDEF000105",
      "order": 17,
      "cp": "",
      "cd": "",
      "title": "Milestone Q",
      "delid": "",
      "FY": "2015",
      "mdps": "11/5/2014",
      "mdpf": "1/31/2015",
      "mdas": "11/5/2014",
      "mdaf": "1/25/2015",
      "pcomp": 0,
      "pqty": 0,
      "oqty": 0,
      "units": "Gallons",
      "status": "Finished On-time",
      "rcc": "",
      "rc": "",
      "phase": "",
      "category": "",
      "leadwc": "",
      "comms": "",
      "duration": 26,
      "delete": "N",
      "uri": "http://localhost:3000/milestones/105"
    },
    {
      "id": 106,
      "index": 2,
      "erpid": "15003",
      "guid": "ABCDEF00-1234-4321-ABCD-ABCDEF000106",
      "order": 4,
      "cp": "",
      "cd": "",
      "title": "Milestone YY",
      "delid": "",
      "FY": "2015",
      "mdps": "3/5/2015",
      "mdpf": "3/31/2015",
      "mdas": "3/5/2015",
      "mdaf": "5/10/2015",
      "pcomp": 0,
      "pqty": 0,
      "oqty": 0,
      "units": "Gallons",
      "status": "Finished Late",
      "rcc": "",
      "rc": "",
      "phase": "",
      "category": "",
      "leadwc": "",
      "comms": "",
      "duration": 26,
      "delete": "N",
      "uri": "http://localhost:3000/milestones/106"
    },
    {
      "id": 200,
      "index": 0,
      "erpid": "16001",
      "guid": "ABCDEF00-1234-4321-ABCD-ABCDEF000200",
      "order": 2,
      "cp": "",
      "cd": "",
      "title": "Milestone A",
      "delid": "",
      "FY": "2016",
      "mdps": "5/5/2016",
      "mdpf": "5/31/2016",
      "mdas": "5/4/2016",
      "mdaf": "5/25/2016",
      "pcomp": 0,
      "pqty": 100,
      "oqty": 70,
      "units": "Drums",
      "status": "Finished On-time",
      "rcc": "",
      "rc": "",
      "phase": "",
      "category": "",
      "leadwc": "",
      "duration": 26,
      "comms": "",
      "uri": "http://localhost:3000/milestones/200"
    },
    {
      "id": 201,
      "index": 1,
      "erpid": "16001",
      "guid": "ABCDEF00-1234-4321-ABCD-ABCDEF000201",
      "order": 1,
      "cp": "",
      "cd": "",
      "title": "Milestone F",
      "delid": "",
      "FY": "2016",
      "mdps": "2/2/2016",
      "mdpf": "3/31/2016",
      "mdas": "2/5/2016",
      "mdaf": "4/4/2016",
      "pcomp": 0,
      "pqty": 10,
      "oqty": 8,
      "units": "Gallons",
      "status": "Finished Late",
      "rcc": "",
      "rc": "",
      "phase": "",
      "category": "",
      "leadwc": "",
      "duration": 26,
      "comms": "",
      "uri": "http://localhost:3000/milestones/201"
    },
    {
      "id": 202,
      "index": 3,
      "erpid": "16001",
      "guid": "ABCDEF00-1234-4321-ABCD-ABCDEF000202",
      "order": 5,
      "cp": "",
      "cd": "",
      "title": "Milestone J",
      "delid": "",
      "FY": "2016",
      "mdps": "8/1/2016",
      "mdpf": "9/6/2016",
      "mdas": "8/5/2016",
      "mdaf": "9/6/2016",
      "pcomp": 0,
      "pqty": 200,
      "oqty": 100,
      "units": "Boxes",
      "status": "Finished On-time",
      "rcc": "",
      "rc": "",
      "phase": "",
      "category": "",
      "leadwc": "",
      "duration": 66,
      "comms": "",
      "uri": "http://localhost:3000/milestones/202"
    },
    {
      "id": 203,
      "index": 2,
      "erpid": "16002",
      "guid": "ABCDEF00-1234-4321-ABCD-ABCDEF000203",
      "order": 4,
      "cp": "",
      "cd": "",
      "title": "Milestone YY",
      "delid": "",
      "FY": "2016",
      "mdps": "1/5/2016",
      "mdpf": "2/14/2016",
      "mdas": "1/5/2016",
      "mdaf": "3/10/2016",
      "pcomp": 0,
      "pqty": 66,
      "oqty": 56,
      "units": "Gallons",
      "status": "Finished Late",
      "rcc": "",
      "rc": "",
      "phase": "",
      "category": "",
      "leadwc": "",
      "duration": 26,
      "comms": "",
      "uri": "http://localhost:3000/milestones/203"
    },
    {
      "id": 204,
      "index": 4,
      "erpid": "16002",
      "guid": "ABCDEF00-1234-4321-ABCD-ABCDEF000204",
      "order": 3,
      "cp": "",
      "cd": "",
      "title": "Milestone TT",
      "delid": "",
      "FY": "2016",
      "mdps": "7/5/2016",
      "mdpf": "7/31/2016",
      "mdas": "5/17/2016",
      "mdaf": "7/7/2016",
      "pcomp": 0,
      "pqty": 50,
      "oqty": 25,
      "units": "Units",
      "status": "Finished On-time",
      "rcc": "",
      "rc": "",
      "phase": "",
      "category": "",
      "leadwc": "",
      "duration": 26,
      "comms": "",
      "uri": "http://localhost:3000/milestones/204"
    },
    {
      "id": 205,
      "index": 0,
      "erpid": "16003",
      "guid": "ABCDEF00-1234-4321-ABCD-ABCDEF000205",
      "order": 17,
      "cp": "",
      "cd": "",
      "title": "Milestone Q",
      "delid": "",
      "FY": "2016",
      "mdps": "11/5/2015",
      "mdpf": "1/31/2016",
      "mdas": "11/5/2015",
      "mdaf": "1/25/2016",
      "pcomp": 0,
      "pqty": 0,
      "oqty": 0,
      "units": "Gallons",
      "status": "Finished On-time",
      "rcc": "",
      "rc": "",
      "phase": "",
      "category": "",
      "leadwc": "",
      "comms": "",
      "duration": 26,
      "delete": "N",
      "uri": "http://localhost:3000/milestones/205"
    },
    {
      "id": 206,
      "index": 2,
      "erpid": "16003",
      "guid": "ABCDEF00-1234-4321-ABCD-ABCDEF000206",
      "order": 4,
      "cp": "",
      "cd": "",
      "title": "Milestone YY",
      "delid": "",
      "FY": "2016",
      "mdps": "3/5/2016",
      "mdpf": "3/31/2016",
      "mdas": "3/5/2016",
      "mdaf": "5/10/2016",
      "pcomp": 0,
      "pqty": 0,
      "oqty": 0,
      "units": "Gallons",
      "status": "Finished Late",
      "rcc": "",
      "rc": "",
      "phase": "",
      "category": "",
      "leadwc": "",
      "comms": "",
      "duration": 26,
      "delete": "N",
      "uri": "http://localhost:3000/milestones/206"
    },
    {
      "id": 300,
      "index": 0,
      "erpid": "17001",
      "guid": "ABCDEF00-1234-4321-ABCD-ABCDEF000300",
      "order": 2,
      "cp": "",
      "cd": "",
      "title": "Milestone A",
      "delid": "",
      "FY": "2017",
      "mdps": "5/5/2017",
      "mdpf": "5/31/2017",
      "mdas": "5/4/2017",
      "mdaf": "5/25/2017",
      "pcomp": 0,
      "pqty": 100,
      "oqty": 70,
      "units": "Drums",
      "status": "Finished On-time",
      "rcc": "",
      "rc": "",
      "phase": "",
      "category": "",
      "leadwc": "",
      "duration": 26,
      "comms": "",
      "uri": "http://localhost:3000/milestones/300"
    },
    {
      "id": 301,
      "index": 1,
      "erpid": "17001",
      "guid": "ABCDEF00-1234-4321-ABCD-ABCDEF000301",
      "order": 1,
      "cp": "",
      "cd": "",
      "title": "Milestone F",
      "delid": "",
      "FY": "2017",
      "mdps": "2/2/2017",
      "mdpf": "3/31/2017",
      "mdas": "2/5/2017",
      "mdaf": "4/4/2017",
      "pcomp": 0,
      "pqty": 10,
      "oqty": 8,
      "units": "Gallons",
      "status": "Finished Late",
      "rcc": "",
      "rc": "",
      "phase": "",
      "category": "",
      "leadwc": "",
      "duration": 26,
      "comms": "",
      "uri": "http://localhost:3000/milestones/301"
    },
    {
      "id": 302,
      "index": 3,
      "erpid": "17001",
      "guid": "ABCDEF00-1234-4321-ABCD-ABCDEF000302",
      "order": 5,
      "cp": "",
      "cd": "",
      "title": "Milestone J",
      "delid": "",
      "FY": "2017",
      "mdps": "8/1/2017",
      "mdpf": "9/6/2017",
      "mdas": "8/5/2017",
      "mdaf": "9/6/2017",
      "pcomp": 0,
      "pqty": 200,
      "oqty": 100,
      "units": "Boxes",
      "status": "Finished On-time",
      "rcc": "",
      "rc": "",
      "phase": "",
      "category": "",
      "leadwc": "",
      "duration": 66,
      "comms": "",
      "uri": "http://localhost:3000/milestones/302"
    },
    {
      "id": 303,
      "index": 2,
      "erpid": "17002",
      "guid": "ABCDEF00-1234-4321-ABCD-ABCDEF000303",
      "order": 4,
      "cp": "",
      "cd": "",
      "title": "Milestone YY",
      "delid": "",
      "FY": "2017",
      "mdps": "1/5/2017",
      "mdpf": "2/14/2017",
      "mdas": "1/5/2017",
      "mdaf": "3/10/2017",
      "pcomp": 0,
      "pqty": 66,
      "oqty": 56,
      "units": "Gallons",
      "status": "Finished Late",
      "rcc": "",
      "rc": "",
      "phase": "",
      "category": "",
      "leadwc": "",
      "duration": 26,
      "comms": "",
      "uri": "http://localhost:3000/milestones/303"
    },
    {
      "id": 304,
      "index": 4,
      "erpid": "17002",
      "guid": "ABCDEF00-1234-4321-ABCD-ABCDEF000304",
      "order": 3,
      "cp": "",
      "cd": "",
      "title": "Milestone TT",
      "delid": "",
      "FY": "2017",
      "mdps": "7/5/2017",
      "mdpf": "7/31/2017",
      "mdas": "5/17/2017",
      "mdaf": "7/7/2017",
      "pcomp": 0,
      "pqty": 50,
      "oqty": 25,
      "units": "Units",
      "status": "Finished On-time",
      "rcc": "",
      "rc": "",
      "phase": "",
      "category": "",
      "leadwc": "",
      "duration": 26,
      "comms": "",
      "uri": "http://localhost:3000/milestones/304"
    },
    {
      "id": 305,
      "index": 0,
      "erpid": "17003",
      "guid": "ABCDEF00-1234-4321-ABCD-ABCDEF000305",
      "order": 17,
      "cp": "",
      "cd": "",
      "title": "Milestone Q",
      "delid": "",
      "FY": "2017",
      "mdps": "11/5/2016",
      "mdpf": "1/31/2017",
      "mdas": "11/5/2016",
      "mdaf": "1/25/2017",
      "pcomp": 0,
      "pqty": 0,
      "oqty": 0,
      "units": "Gallons",
      "status": "Finished On-time",
      "rcc": "",
      "rc": "",
      "phase": "",
      "category": "",
      "leadwc": "",
      "comms": "",
      "duration": 26,
      "delete": "N",
      "uri": "http://localhost:3000/milestones/305"
    },
    {
      "id": 306,
      "index": 2,
      "erpid": "17003",
      "guid": "ABCDEF00-1234-4321-ABCD-ABCDEF000306",
      "order": 4,
      "cp": "",
      "cd": "",
      "title": "Milestone YY",
      "delid": "",
      "FY": "2017",
      "mdps": "3/5/2017",
      "mdpf": "3/31/2017",
      "mdas": "3/5/2017",
      "mdaf": "5/10/2017",
      "pcomp": 0,
      "pqty": 0,
      "oqty": 0,
      "units": "Gallons",
      "status": "Finished Late",
      "rcc": "",
      "rc": "",
      "phase": "",
      "category": "",
      "leadwc": "",
      "comms": "",
      "duration": 26,
      "delete": "N",
      "uri": "http://localhost:3000/milestones/306"
    },
    {
      "id": 400,
      "index": 0,
      "erpid": "18001",
      "guid": "ABCDEF00-1234-4321-ABCD-ABCDEF000400",
      "order": 2,
      "cp": "",
      "cd": "",
      "title": "Milestone A",
      "delid": "",
      "FY": "2018",
      "mdps": "5/5/2018",
      "mdpf": "5/31/2018",
      "mdas": "5/4/2018",
      "mdaf": "5/25/2018",
      "pcomp": 0,
      "pqty": 100,
      "oqty": 70,
      "units": "Drums",
      "status": "Finished On-time",
      "rcc": "",
      "rc": "",
      "phase": "",
      "category": "",
      "leadwc": "",
      "duration": 26,
      "comms": "",
      "uri": "http://localhost:3000/milestones/400"
    },
    {
      "id": 401,
      "index": 1,
      "erpid": "18001",
      "guid": "ABCDEF00-1234-4321-ABCD-ABCDEF000401",
      "order": 1,
      "cp": "",
      "cd": "",
      "title": "Milestone F",
      "delid": "",
      "FY": "2018",
      "mdps": "2/2/2018",
      "mdpf": "3/31/2018",
      "mdas": "2/5/2018",
      "mdaf": "4/4/2018",
      "pcomp": 0,
      "pqty": 10,
      "oqty": 8,
      "units": "Gallons",
      "status": "Finished Late",
      "rcc": "",
      "rc": "",
      "phase": "",
      "category": "",
      "leadwc": "",
      "duration": 26,
      "comms": "",
      "uri": "http://localhost:3000/milestones/401"
    },
    {
      "id": 402,
      "index": 3,
      "erpid": "18001",
      "guid": "ABCDEF00-1234-4321-ABCD-ABCDEF000402",
      "order": 5,
      "cp": "",
      "cd": "",
      "title": "Milestone J",
      "delid": "",
      "FY": "2018",
      "mdps": "8/1/2018",
      "mdpf": "9/6/2018",
      "mdas": "8/5/2018",
      "mdaf": "9/6/2018",
      "pcomp": 0,
      "pqty": 200,
      "oqty": 100,
      "units": "Boxes",
      "status": "Finished On-time",
      "rcc": "",
      "rc": "",
      "phase": "",
      "category": "",
      "leadwc": "",
      "duration": 66,
      "comms": "",
      "uri": "http://localhost:3000/milestones/402"
    },
    {
      "id": 403,
      "index": 2,
      "erpid": "18001",
      "guid": "ABCDEF00-1234-4321-ABCD-ABCDEF000403",
      "order": 4,
      "cp": "",
      "cd": "",
      "title": "Milestone YY",
      "delid": "",
      "FY": "2018",
      "mdps": "1/5/2018",
      "mdpf": "2/14/2018",
      "mdas": "1/5/2018",
      "mdaf": "3/10/2018",
      "pcomp": 0,
      "pqty": 66,
      "oqty": 56,
      "units": "Gallons",
      "status": "Finished Late",
      "rcc": "",
      "rc": "",
      "phase": "",
      "category": "",
      "leadwc": "",
      "duration": 26,
      "comms": "",
      "uri": "http://localhost:3000/milestones/403"
    },
    {
      "id": 404,
      "index": 4,
      "erpid": "18002",
      "guid": "ABCDEF00-1234-4321-ABCD-ABCDEF000404",
      "order": 3,
      "cp": "",
      "cd": "",
      "title": "Milestone TT",
      "delid": "",
      "FY": "2018",
      "mdps": "7/5/2018",
      "mdpf": "7/31/2018",
      "mdas": "5/17/2018",
      "mdaf": "7/7/2018",
      "pcomp": 0,
      "pqty": 50,
      "oqty": 25,
      "units": "Units",
      "status": "Finished On-time",
      "rcc": "",
      "rc": "",
      "phase": "",
      "category": "",
      "leadwc": "",
      "duration": 26,
      "comms": "",
      "uri": "http://localhost:3000/milestones/404"
    },
    {
      "id": 405,
      "index": 0,
      "erpid": "18002",
      "guid": "ABCDEF00-1234-4321-ABCD-ABCDEF000405",
      "order": 17,
      "cp": "",
      "cd": "",
      "title": "Milestone Q",
      "delid": "",
      "FY": "2018",
      "mdps": "11/5/2017",
      "mdpf": "1/31/2018",
      "mdas": "11/5/2017",
      "mdaf": "1/25/2018",
      "pcomp": 0,
      "pqty": 0,
      "oqty": 0,
      "units": "Gallons",
      "status": "Finished On-time",
      "rcc": "",
      "rc": "",
      "phase": "",
      "category": "",
      "leadwc": "",
      "comms": "",
      "duration": 26,
      "delete": "N",
      "uri": "http://localhost:3000/milestones/405"
    },
    {
      "id": 406,
      "index": 2,
      "erpid": "18003",
      "guid": "ABCDEF00-1234-4321-ABCD-ABCDEF000406",
      "order": 4,
      "cp": "",
      "cd": "",
      "title": "Milestone YY",
      "delid": "",
      "FY": "2018",
      "mdps": "3/5/2018",
      "mdpf": "3/31/2018",
      "mdas": "3/5/2018",
      "mdaf": "5/10/2018",
      "pcomp": 0,
      "pqty": 0,
      "oqty": 0,
      "units": "Gallons",
      "status": "Finished Late",
      "rcc": "",
      "rc": "",
      "phase": "",
      "category": "",
      "leadwc": "",
      "comms": "",
      "duration": 26,
      "delete": "N",
      "uri": "http://localhost:3000/milestones/406"
    },
    {
      "id": 500,
      "index": 0,
      "erpid": "20001",
      "guid": "ABCDEF00-1234-4321-ABCD-ABCDEF000500",
      "order": 2,
      "cp": "",
      "cd": "",
      "title": "Milestone A",
      "delid": "",
      "FY": "2020",
      "mdps": "5/5/2020",
      "mdpf": "5/31/2020",
      "mdas": "5/4/2020",
      "mdaf": "5/25/2020",
      "pcomp": 0,
      "pqty": 100,
      "oqty": 70,
      "units": "Drums",
      "status": "Finished On-time",
      "rcc": "",
      "rc": "",
      "phase": "",
      "category": "",
      "leadwc": "",
      "duration": 26,
      "comms": "",
      "uri": "http://localhost:3000/milestones/500"
    },
    {
      "id": 501,
      "index": 1,
      "erpid": "20001",
      "guid": "ABCDEF00-1234-4321-ABCD-ABCDEF000501",
      "order": 1,
      "cp": "",
      "cd": "",
      "title": "Milestone F",
      "delid": "",
      "FY": "2020",
      "mdps": "2/2/2020",
      "mdpf": "3/31/2020",
      "mdas": "2/5/2020",
      "mdaf": "4/4/2020",
      "pcomp": 0,
      "pqty": 10,
      "oqty": 8,
      "units": "Gallons",
      "status": "Finished Late",
      "rcc": "",
      "rc": "",
      "phase": "",
      "category": "",
      "leadwc": "",
      "duration": 26,
      "comms": "",
      "uri": "http://localhost:3000/milestones/501"
    },
    {
      "id": 502,
      "index": 3,
      "erpid": "20001",
      "guid": "ABCDEF00-1234-4321-ABCD-ABCDEF000502",
      "order": 5,
      "cp": "",
      "cd": "",
      "title": "Milestone J",
      "delid": "",
      "FY": "2020",
      "mdps": "8/1/2020",
      "mdpf": "9/6/2020",
      "mdas": "8/5/2020",
      "mdaf": "9/6/2020",
      "pcomp": 0,
      "pqty": 200,
      "oqty": 100,
      "units": "Boxes",
      "status": "Finished On-time",
      "rcc": "",
      "rc": "",
      "phase": "",
      "category": "",
      "leadwc": "",
      "duration": 66,
      "comms": "",
      "uri": "http://localhost:3000/milestones/502"
    },
    {
      "id": 503,
      "index": 2,
      "erpid": "20003",
      "guid": "ABCDEF00-1234-4321-ABCD-ABCDEF000503",
      "order": 4,
      "cp": "",
      "cd": "",
      "title": "Milestone YYA",
      "delid": "",
      "FY": "2020",
      "mdps": "1/5/2020",
      "mdpf": "2/14/2020",
      "mdas": "1/5/2020",
      "mdaf": "3/10/2020",
      "pcomp": 0,
      "pqty": 66,
      "oqty": 56,
      "units": "Gallons",
      "status": "Finished Late",
      "rcc": "",
      "rc": "",
      "phase": "",
      "category": "",
      "leadwc": "",
      "duration": 26,
      "comms": "",
      "uri": "http://localhost:3000/milestones/503"
    },
    {
      "id": 504,
      "index": 4,
      "erpid": "20003",
      "guid": "ABCDEF00-1234-4321-ABCD-ABCDEF000504",
      "order": 3,
      "cp": "",
      "cd": "",
      "title": "Milestone TT",
      "delid": "",
      "FY": "2020",
      "mdps": "7/5/2020",
      "mdpf": "7/31/2020",
      "mdas": "5/17/2020",
      "mdaf": "7/7/2020",
      "pcomp": 0,
      "pqty": 50,
      "oqty": 25,
      "units": "Units",
      "status": "Finished On-time",
      "rcc": "",
      "rc": "",
      "phase": "",
      "category": "",
      "leadwc": "",
      "duration": 26,
      "comms": "",
      "uri": "http://localhost:3000/milestones/504"
    },
    {
      "id": 505,
      "index": 0,
      "erpid": "20002",
      "guid": "ABCDEF00-1234-4321-ABCD-ABCDEF000505",
      "order": 17,
      "cp": "",
      "cd": "",
      "title": "Milestone Q",
      "delid": "",
      "FY": "2020",
      "mdps": "11/5/2019",
      "mdpf": "1/31/2020",
      "mdas": "11/5/2019",
      "mdaf": "1/25/2020",
      "pcomp": 0,
      "pqty": 0,
      "oqty": 0,
      "units": "Gallons",
      "status": "Finished On-time",
      "rcc": "",
      "rc": "",
      "phase": "",
      "category": "",
      "leadwc": "",
      "comms": "",
      "duration": 26,
      "delete": "N",
      "uri": "http://localhost:3000/milestones/505"
    },
    {
      "id": 506,
      "index": 2,
      "erpid": "20001",
      "guid": "ABCDEF00-1234-4321-ABCD-ABCDEF000506",
      "order": 4,
      "cp": "",
      "cd": "",
      "title": "Milestone YY",
      "delid": "",
      "FY": "2020",
      "mdps": "3/5/2020",
      "mdpf": "3/31/2020",
      "mdas": "3/5/2020",
      "mdaf": "5/10/2020",
      "pcomp": 0,
      "pqty": 0,
      "oqty": 0,
      "units": "Gallons",
      "status": "Finished Late",
      "rcc": "",
      "rc": "",
      "phase": "",
      "category": "",
      "leadwc": "",
      "comms": "",
      "duration": 26,
      "delete": "N",
      "uri": "http://localhost:3000/milestones/506"
    },
    {
      "id": 507,
      "index": 0,
      "erpid": "20002",
      "guid": "ABCDEF00-1234-4321-ABCD-ABCDEF000507",
      "order": 2,
      "cp": "",
      "cd": "",
      "title": "Milestone AA",
      "delid": "",
      "FY": "2020",
      "mdps": "5/5/2020",
      "mdpf": "5/31/2020",
      "mdas": "5/4/2020",
      "mdaf": "5/25/2020",
      "pcomp": 0,
      "pqty": 100,
      "oqty": 70,
      "units": "Drums",
      "status": "Finished On-time",
      "rcc": "",
      "rc": "",
      "phase": "",
      "category": "",
      "leadwc": "",
      "duration": 26,
      "comms": "",
      "uri": "http://localhost:3000/milestones/507"
    },
    {
      "id": 508,
      "index": 1,
      "erpid": "20002",
      "guid": "ABCDEF00-1234-4321-ABCD-ABCDEF000508",
      "order": 1,
      "cp": "",
      "cd": "",
      "title": "Milestone FA",
      "delid": "",
      "FY": "2020",
      "mdps": "2/2/2020",
      "mdpf": "3/31/2020",
      "mdas": "2/5/2020",
      "mdaf": "4/4/2020",
      "pcomp": 0,
      "pqty": 10,
      "oqty": 8,
      "units": "Gallons",
      "status": "Finished Late",
      "rcc": "",
      "rc": "",
      "phase": "",
      "category": "",
      "leadwc": "",
      "duration": 26,
      "comms": "",
      "uri": "http://localhost:3000/milestones/508"
    },
    {
      "id": 509,
      "index": 3,
      "erpid": "20001",
      "guid": "ABCDEF00-1234-4321-ABCD-ABCDEF000509",
      "order": 5,
      "cp": "",
      "cd": "",
      "title": "Milestone JA",
      "delid": "",
      "FY": "2020",
      "mdps": "8/1/2020",
      "mdpf": "9/6/2020",
      "mdas": "8/5/2020",
      "mdaf": "9/6/2020",
      "pcomp": 0,
      "pqty": 200,
      "oqty": 100,
      "units": "Boxes",
      "status": "Finished On-time",
      "rcc": "",
      "rc": "",
      "phase": "",
      "category": "",
      "leadwc": "",
      "duration": 66,
      "comms": "",
      "uri": "http://localhost:3000/milestones/509"
    },
    {
      "id": 510,
      "index": 2,
      "erpid": "20003",
      "guid": "ABCDEF00-1234-4321-ABCD-ABCDEF000510",
      "order": 4,
      "cp": "",
      "cd": "",
      "title": "Milestone YAY",
      "delid": "",
      "FY": "2020",
      "mdps": "1/5/2020",
      "mdpf": "2/14/2020",
      "mdas": "1/5/2020",
      "mdaf": "3/10/2020",
      "pcomp": 0,
      "pqty": 66,
      "oqty": 56,
      "units": "Gallons",
      "status": "Finished Late",
      "rcc": "",
      "rc": "",
      "phase": "",
      "category": "",
      "leadwc": "",
      "duration": 26,
      "comms": "",
      "uri": "http://localhost:3000/milestones/510"
    },
    {
      "id": 511,
      "index": 4,
      "erpid": "20001",
      "guid": "ABCDEF00-1234-4321-ABCD-ABCDEF000511",
      "order": 3,
      "cp": "",
      "cd": "",
      "title": "Milestone ATAT",
      "delid": "",
      "FY": "2020",
      "mdps": "7/5/2020",
      "mdpf": "7/31/2020",
      "mdas": "5/17/2020",
      "mdaf": "7/7/2020",
      "pcomp": 0,
      "pqty": 50,
      "oqty": 25,
      "units": "Units",
      "status": "Finished On-time",
      "rcc": "",
      "rc": "",
      "phase": "",
      "category": "",
      "leadwc": "",
      "duration": 26,
      "comms": "",
      "uri": "http://localhost:3000/milestones/511"
    },
    {
      "id": 512,
      "index": 0,
      "erpid": "20001",
      "guid": "ABCDEF00-1234-4321-ABCD-ABCDEF000512",
      "order": 17,
      "cp": "",
      "cd": "",
      "title": "Milestone QA",
      "delid": "",
      "FY": "2020",
      "mdps": "11/5/2019",
      "mdpf": "1/31/2020",
      "mdas": "11/5/2019",
      "mdaf": "1/25/2020",
      "pcomp": 0,
      "pqty": 0,
      "oqty": 0,
      "units": "Gallons",
      "status": "Finished On-time",
      "rcc": "",
      "rc": "",
      "phase": "",
      "category": "",
      "leadwc": "",
      "comms": "",
      "duration": 26,
      "delete": "N",
      "uri": "http://localhost:3000/milestones/512"
    },
    {
      "id": 513,
      "index": 2,
      "erpid": "20003",
      "guid": "ABCDEF00-1234-4321-ABCD-ABCDEF000513",
      "order": 4,
      "cp": "",
      "cd": "",
      "title": "Milestone AYY",
      "delid": "",
      "FY": "2020",
      "mdps": "3/5/2020",
      "mdpf": "3/31/2020",
      "mdas": "3/5/2020",
      "mdaf": "5/10/2020",
      "pcomp": 0,
      "pqty": 0,
      "oqty": 0,
      "units": "Gallons",
      "status": "Finished Late",
      "rcc": "",
      "rc": "",
      "phase": "",
      "category": "",
      "leadwc": "",
      "comms": "",
      "duration": 26,
      "delete": "N",
      "uri": "http://localhost:3000/milestones/513"
    },
    {
      "id": 1500,
      "index": 0,
      "erpid": "20001",
      "guid": "ABCDEF00-1234-4321-ABCD-ABCDEF000500",
      "order": 2,
      "cp": "",
      "cd": "",
      "title": "Milestone A",
      "delid": "",
      "FY": "2015",
      "mdps": "10/5/2014",
      "mdpf": "10/31/2014",
      "mdas": "10/4/2014",
      "mdaf": "10/25/2014",
      "pcomp": 0,
      "pqty": 100,
      "oqty": 70,
      "units": "Drums",
      "status": "Finished On-time",
      "rcc": "",
      "rc": "",
      "phase": "",
      "category": "",
      "leadwc": "",
      "duration": 26,
      "comms": "",
      "uri": "http://localhost:3000/milestones/1500"
    },
    {
      "id": 1501,
      "index": 1,
      "erpid": "20001",
      "guid": "ABCDEF00-1234-4321-ABCD-ABCDEF000501",
      "order": 1,
      "cp": "",
      "cd": "",
      "title": "Milestone F",
      "delid": "",
      "FY": "2015",
      "mdps": "11/2/2014",
      "mdpf": "11/28/2014",
      "mdas": "11/5/2014",
      "mdaf": "12/4/2014",
      "pcomp": 0,
      "pqty": 10,
      "oqty": 8,
      "units": "Gallons",
      "status": "Finished Late",
      "rcc": "",
      "rc": "",
      "phase": "",
      "category": "",
      "leadwc": "",
      "duration": 26,
      "comms": "",
      "uri": "http://localhost:3000/milestones/501"
    },
    {
      "id": 1502,
      "index": 3,
      "erpid": "20001",
      "guid": "ABCDEF00-1234-4321-ABCD-ABCDEF000502",
      "order": 5,
      "cp": "",
      "cd": "",
      "title": "Milestone J",
      "delid": "",
      "FY": "2015",
      "mdps": "12/1/2014",
      "mdpf": "12/16/2014",
      "mdas": "11/30/2014",
      "mdaf": "12/6/2014",
      "pcomp": 0,
      "pqty": 200,
      "oqty": 100,
      "units": "Boxes",
      "status": "Finished On-time",
      "rcc": "",
      "rc": "",
      "phase": "",
      "category": "",
      "leadwc": "",
      "duration": 66,
      "comms": "",
      "uri": "http://localhost:3000/milestones/502"
    },
    {
      "id": 1503,
      "index": 2,
      "erpid": "20003",
      "guid": "ABCDEF00-1234-4321-ABCD-ABCDEF000503",
      "order": 4,
      "cp": "",
      "cd": "",
      "title": "Milestone YYA",
      "delid": "",
      "FY": "2015",
      "mdps": "1/5/2015",
      "mdpf": "1/14/2015",
      "mdas": "1/5/2015",
      "mdaf": "3/10/2015",
      "pcomp": 0,
      "pqty": 66,
      "oqty": 56,
      "units": "Gallons",
      "status": "Finished Late",
      "rcc": "",
      "rc": "",
      "phase": "",
      "category": "",
      "leadwc": "",
      "duration": 26,
      "comms": "",
      "uri": "http://localhost:3000/milestones/503"
    },
    {
      "id": 1504,
      "index": 4,
      "erpid": "20003",
      "guid": "ABCDEF00-1234-4321-ABCD-ABCDEF000504",
      "order": 3,
      "cp": "",
      "cd": "",
      "title": "Milestone TT",
      "delid": "",
      "FY": "2015",
      "mdps": "2/5/2015",
      "mdpf": "2/28/2015",
      "mdas": "2/2/2015",
      "mdaf": "2/27/2015",
      "pcomp": 0,
      "pqty": 50,
      "oqty": 25,
      "units": "Units",
      "status": "Finished On-time",
      "rcc": "",
      "rc": "",
      "phase": "",
      "category": "",
      "leadwc": "",
      "duration": 26,
      "comms": "",
      "uri": "http://localhost:3000/milestones/504"
    },
    {
      "id": 1505,
      "index": 0,
      "erpid": "20002",
      "guid": "ABCDEF00-1234-4321-ABCD-ABCDEF000505",
      "order": 17,
      "cp": "",
      "cd": "",
      "title": "Milestone Q",
      "delid": "",
      "FY": "2015",
      "mdps": "2/5/2015",
      "mdpf": "3/31/2015",
      "mdas": "2/5/2015",
      "mdaf": "3/25/2015",
      "pcomp": 0,
      "pqty": 0,
      "oqty": 0,
      "units": "Gallons",
      "status": "Finished On-time",
      "rcc": "",
      "rc": "",
      "phase": "",
      "category": "",
      "leadwc": "",
      "comms": "",
      "duration": 26,
      "delete": "N",
      "uri": "http://localhost:3000/milestones/505"
    },
    {
      "id": 1506,
      "index": 2,
      "erpid": "20001",
      "guid": "ABCDEF00-1234-4321-ABCD-ABCDEF000506",
      "order": 4,
      "cp": "",
      "cd": "",
      "title": "Milestone YY",
      "delid": "",
      "FY": "2015",
      "mdps": "3/5/2015",
      "mdpf": "4/30/2015",
      "mdas": "3/5/2015",
      "mdaf": "5/10/2015",
      "pcomp": 0,
      "pqty": 0,
      "oqty": 0,
      "units": "Gallons",
      "status": "Finished Late",
      "rcc": "",
      "rc": "",
      "phase": "",
      "category": "",
      "leadwc": "",
      "comms": "",
      "duration": 26,
      "delete": "N",
      "uri": "http://localhost:3000/milestones/506"
    },
    {
      "id": 1507,
      "index": 0,
      "erpid": "20002",
      "guid": "ABCDEF00-1234-4321-ABCD-ABCDEF000507",
      "order": 2,
      "cp": "",
      "cd": "",
      "title": "Milestone AA",
      "delid": "",
      "FY": "2015",
      "mdps": "5/5/2015",
      "mdpf": "5/31/2015",
      "mdas": "5/4/2015",
      "mdaf": "5/25/2015",
      "pcomp": 0,
      "pqty": 100,
      "oqty": 70,
      "units": "Drums",
      "status": "Finished On-time",
      "rcc": "",
      "rc": "",
      "phase": "",
      "category": "",
      "leadwc": "",
      "duration": 26,
      "comms": "",
      "uri": "http://localhost:3000/milestones/507"
    },
    {
      "id": 1508,
      "index": 1,
      "erpid": "20002",
      "guid": "ABCDEF00-1234-4321-ABCD-ABCDEF000508",
      "order": 1,
      "cp": "",
      "cd": "",
      "title": "Milestone FA",
      "delid": "",
      "FY": "2015",
      "mdps": "2/2/2015",
      "mdpf": "6/26/2015",
      "mdas": "2/5/2015",
      "mdaf": "7/1/2015",
      "pcomp": 0,
      "pqty": 10,
      "oqty": 8,
      "units": "Gallons",
      "status": "Finished Late",
      "rcc": "",
      "rc": "",
      "phase": "",
      "category": "",
      "leadwc": "",
      "duration": 26,
      "comms": "",
      "uri": "http://localhost:3000/milestones/508"
    },
    {
      "id": 1509,
      "index": 3,
      "erpid": "20001",
      "guid": "ABCDEF00-1234-4321-ABCD-ABCDEF000509",
      "order": 5,
      "cp": "",
      "cd": "",
      "title": "Milestone JA",
      "delid": "",
      "FY": "2015",
      "mdps": "6/1/2015",
      "mdpf": "7/16/2015",
      "mdas": "6/5/2015",
      "mdaf": "7/6/2015",
      "pcomp": 0,
      "pqty": 200,
      "oqty": 100,
      "units": "Boxes",
      "status": "Finished On-time",
      "rcc": "",
      "rc": "",
      "phase": "",
      "category": "",
      "leadwc": "",
      "duration": 66,
      "comms": "",
      "uri": "http://localhost:3000/milestones/509"
    },
    {
      "id": 1510,
      "index": 2,
      "erpid": "20003",
      "guid": "ABCDEF00-1234-4321-ABCD-ABCDEF000510",
      "order": 4,
      "cp": "",
      "cd": "",
      "title": "Milestone YAY",
      "delid": "",
      "FY": "2015",
      "mdps": "6/5/2015",
      "mdpf": "8/14/2015",
      "mdas": "6/5/2015",
      "mdaf": "9/10/2015",
      "pcomp": 0,
      "pqty": 66,
      "oqty": 56,
      "units": "Gallons",
      "status": "Finished Late",
      "rcc": "",
      "rc": "",
      "phase": "",
      "category": "",
      "leadwc": "",
      "duration": 26,
      "comms": "",
      "uri": "http://localhost:3000/milestones/510"
    },
    {
      "id": 1511,
      "index": 4,
      "erpid": "20001",
      "guid": "ABCDEF00-1234-4321-ABCD-ABCDEF000511",
      "order": 3,
      "cp": "",
      "cd": "",
      "title": "Milestone ATAT",
      "delid": "",
      "FY": "2015",
      "mdps": "7/5/2015",
      "mdpf": "8/30/2015",
      "mdas": "5/17/2015",
      "mdaf": "8/7/2015",
      "pcomp": 0,
      "pqty": 50,
      "oqty": 25,
      "units": "Units",
      "status": "Finished On-time",
      "rcc": "",
      "rc": "",
      "phase": "",
      "category": "",
      "leadwc": "",
      "duration": 26,
      "comms": "",
      "uri": "http://localhost:3000/milestones/511"
    },
    {
      "id": 1512,
      "index": 0,
      "erpid": "20001",
      "guid": "ABCDEF00-1234-4321-ABCD-ABCDEF000512",
      "order": 17,
      "cp": "",
      "cd": "",
      "title": "Milestone QA",
      "delid": "",
      "FY": "2015",
      "mdps": "8/5/2015",
      "mdpf": "9/29/2015",
      "mdas": "8/5/2015",
      "mdaf": "9/25/2015",
      "pcomp": 0,
      "pqty": 0,
      "oqty": 0,
      "units": "Gallons",
      "status": "Finished On-time",
      "rcc": "",
      "rc": "",
      "phase": "",
      "category": "",
      "leadwc": "",
      "comms": "",
      "duration": 26,
      "delete": "N",
      "uri": "http://localhost:3000/milestones/512"
    },
    {
      "id": 1513,
      "index": 2,
      "erpid": "20003",
      "guid": "ABCDEF00-1234-4321-ABCD-ABCDEF000513",
      "order": 4,
      "cp": "",
      "cd": "",
      "title": "Milestone AYY",
      "delid": "",
      "FY": "2015",
      "mdps": "8/5/2015",
      "mdpf": "9/18/2015",
      "mdas": "8/15/2015",
      "mdaf": "9/22/2015",
      "pcomp": 0,
      "pqty": 0,
      "oqty": 0,
      "units": "Gallons",
      "status": "Finished Late",
      "rcc": "",
      "rc": "",
      "phase": "",
      "category": "",
      "leadwc": "",
      "comms": "",
      "duration": 26,
      "delete": "N",
      "uri": "http://localhost:3000/milestones/513"
    },
    {
      "id": 1500,
      "index": 0,
      "erpid": "20001",
      "guid": "ABCDEF00-1234-4321-ABCD-ABCDEF000500",
      "order": 2,
      "cp": "",
      "cd": "",
      "title": "Milestone A",
      "delid": "",
      "FY": "2016",
      "mdps": "10/5/2015",
      "mdpf": "10/31/2015",
      "mdas": "10/4/2015",
      "mdaf": "10/25/2015",
      "pcomp": 0,
      "pqty": 100,
      "oqty": 70,
      "units": "Drums",
      "status": "Finished On-time",
      "rcc": "",
      "rc": "",
      "phase": "",
      "category": "",
      "leadwc": "",
      "duration": 26,
      "comms": "",
      "uri": "http://localhost:3000/milestones/1500"
    },
    {
      "id": 1501,
      "index": 1,
      "erpid": "20001",
      "guid": "ABCDEF00-1234-4321-ABCD-ABCDEF000501",
      "order": 1,
      "cp": "",
      "cd": "",
      "title": "Milestone F",
      "delid": "",
      "FY": "2016",
      "mdps": "11/2/2015",
      "mdpf": "11/28/2015",
      "mdas": "11/5/2015",
      "mdaf": "12/4/2015",
      "pcomp": 0,
      "pqty": 10,
      "oqty": 8,
      "units": "Gallons",
      "status": "Finished Late",
      "rcc": "",
      "rc": "",
      "phase": "",
      "category": "",
      "leadwc": "",
      "duration": 26,
      "comms": "",
      "uri": "http://localhost:3000/milestones/501"
    },
    {
      "id": 1502,
      "index": 3,
      "erpid": "20001",
      "guid": "ABCDEF00-1234-4321-ABCD-ABCDEF000502",
      "order": 5,
      "cp": "",
      "cd": "",
      "title": "Milestone J",
      "delid": "",
      "FY": "2016",
      "mdps": "12/1/2015",
      "mdpf": "12/16/2015",
      "mdas": "11/30/2015",
      "mdaf": "12/6/2015",
      "pcomp": 0,
      "pqty": 200,
      "oqty": 100,
      "units": "Boxes",
      "status": "Finished On-time",
      "rcc": "",
      "rc": "",
      "phase": "",
      "category": "",
      "leadwc": "",
      "duration": 66,
      "comms": "",
      "uri": "http://localhost:3000/milestones/502"
    },
    {
      "id": 1503,
      "index": 2,
      "erpid": "20003",
      "guid": "ABCDEF00-1234-4321-ABCD-ABCDEF000503",
      "order": 4,
      "cp": "",
      "cd": "",
      "title": "Milestone YYA",
      "delid": "",
      "FY": "2016",
      "mdps": "1/5/2016",
      "mdpf": "1/14/2016",
      "mdas": "1/5/2016",
      "mdaf": "3/10/2016",
      "pcomp": 0,
      "pqty": 66,
      "oqty": 56,
      "units": "Gallons",
      "status": "Finished Late",
      "rcc": "",
      "rc": "",
      "phase": "",
      "category": "",
      "leadwc": "",
      "duration": 26,
      "comms": "",
      "uri": "http://localhost:3000/milestones/503"
    },
    {
      "id": 1504,
      "index": 4,
      "erpid": "20003",
      "guid": "ABCDEF00-1234-4321-ABCD-ABCDEF000504",
      "order": 3,
      "cp": "",
      "cd": "",
      "title": "Milestone TT",
      "delid": "",
      "FY": "2016",
      "mdps": "2/5/2016",
      "mdpf": "2/28/2016",
      "mdas": "2/2/2016",
      "mdaf": "2/27/2016",
      "pcomp": 0,
      "pqty": 50,
      "oqty": 25,
      "units": "Units",
      "status": "Finished On-time",
      "rcc": "",
      "rc": "",
      "phase": "",
      "category": "",
      "leadwc": "",
      "duration": 26,
      "comms": "",
      "uri": "http://localhost:3000/milestones/504"
    },
    {
      "id": 1505,
      "index": 0,
      "erpid": "20002",
      "guid": "ABCDEF00-1234-4321-ABCD-ABCDEF000505",
      "order": 17,
      "cp": "",
      "cd": "",
      "title": "Milestone Q",
      "delid": "",
      "FY": "2016",
      "mdps": "2/5/2016",
      "mdpf": "3/31/2016",
      "mdas": "2/5/2016",
      "mdaf": "3/25/2016",
      "pcomp": 0,
      "pqty": 0,
      "oqty": 0,
      "units": "Gallons",
      "status": "Finished On-time",
      "rcc": "",
      "rc": "",
      "phase": "",
      "category": "",
      "leadwc": "",
      "comms": "",
      "duration": 26,
      "delete": "N",
      "uri": "http://localhost:3000/milestones/505"
    },
    {
      "id": 1506,
      "index": 2,
      "erpid": "20001",
      "guid": "ABCDEF00-1234-4321-ABCD-ABCDEF000506",
      "order": 4,
      "cp": "",
      "cd": "",
      "title": "Milestone YY",
      "delid": "",
      "FY": "2016",
      "mdps": "3/5/2016",
      "mdpf": "4/30/2016",
      "mdas": "3/5/2016",
      "mdaf": "5/10/2016",
      "pcomp": 0,
      "pqty": 0,
      "oqty": 0,
      "units": "Gallons",
      "status": "Finished Late",
      "rcc": "",
      "rc": "",
      "phase": "",
      "category": "",
      "leadwc": "",
      "comms": "",
      "duration": 26,
      "delete": "N",
      "uri": "http://localhost:3000/milestones/506"
    },
    {
      "id": 1507,
      "index": 0,
      "erpid": "20002",
      "guid": "ABCDEF00-1234-4321-ABCD-ABCDEF000507",
      "order": 2,
      "cp": "",
      "cd": "",
      "title": "Milestone AA",
      "delid": "",
      "FY": "2016",
      "mdps": "5/5/2016",
      "mdpf": "5/31/2016",
      "mdas": "5/4/2016",
      "mdaf": "5/25/2016",
      "pcomp": 0,
      "pqty": 100,
      "oqty": 70,
      "units": "Drums",
      "status": "Finished On-time",
      "rcc": "",
      "rc": "",
      "phase": "",
      "category": "",
      "leadwc": "",
      "duration": 26,
      "comms": "",
      "uri": "http://localhost:3000/milestones/507"
    },
    {
      "id": 1508,
      "index": 1,
      "erpid": "20002",
      "guid": "ABCDEF00-1234-4321-ABCD-ABCDEF000508",
      "order": 1,
      "cp": "",
      "cd": "",
      "title": "Milestone FA",
      "delid": "",
      "FY": "2016",
      "mdps": "2/2/2016",
      "mdpf": "6/26/2016",
      "mdas": "2/5/2016",
      "mdaf": "7/1/2016",
      "pcomp": 0,
      "pqty": 10,
      "oqty": 8,
      "units": "Gallons",
      "status": "Finished Late",
      "rcc": "",
      "rc": "",
      "phase": "",
      "category": "",
      "leadwc": "",
      "duration": 26,
      "comms": "",
      "uri": "http://localhost:3000/milestones/508"
    },
    {
      "id": 1509,
      "index": 3,
      "erpid": "20001",
      "guid": "ABCDEF00-1234-4321-ABCD-ABCDEF000509",
      "order": 5,
      "cp": "",
      "cd": "",
      "title": "Milestone JA",
      "delid": "",
      "FY": "2016",
      "mdps": "6/1/2016",
      "mdpf": "7/16/2016",
      "mdas": "6/5/2016",
      "mdaf": "7/6/2016",
      "pcomp": 0,
      "pqty": 200,
      "oqty": 100,
      "units": "Boxes",
      "status": "Finished On-time",
      "rcc": "",
      "rc": "",
      "phase": "",
      "category": "",
      "leadwc": "",
      "duration": 66,
      "comms": "",
      "uri": "http://localhost:3000/milestones/509"
    },
    {
      "id": 1510,
      "index": 2,
      "erpid": "20003",
      "guid": "ABCDEF00-1234-4321-ABCD-ABCDEF000510",
      "order": 4,
      "cp": "",
      "cd": "",
      "title": "Milestone YAY",
      "delid": "",
      "FY": "2016",
      "mdps": "6/5/2016",
      "mdpf": "8/14/2016",
      "mdas": "6/5/2016",
      "mdaf": "9/10/2016",
      "pcomp": 0,
      "pqty": 66,
      "oqty": 56,
      "units": "Gallons",
      "status": "Finished Late",
      "rcc": "",
      "rc": "",
      "phase": "",
      "category": "",
      "leadwc": "",
      "duration": 26,
      "comms": "",
      "uri": "http://localhost:3000/milestones/510"
    },
    {
      "id": 1511,
      "index": 4,
      "erpid": "20001",
      "guid": "ABCDEF00-1234-4321-ABCD-ABCDEF000511",
      "order": 3,
      "cp": "",
      "cd": "",
      "title": "Milestone ATAT",
      "delid": "",
      "FY": "2016",
      "mdps": "7/5/2016",
      "mdpf": "8/30/2016",
      "mdas": "5/17/2016",
      "mdaf": "8/7/2016",
      "pcomp": 0,
      "pqty": 50,
      "oqty": 25,
      "units": "Units",
      "status": "Finished On-time",
      "rcc": "",
      "rc": "",
      "phase": "",
      "category": "",
      "leadwc": "",
      "duration": 26,
      "comms": "",
      "uri": "http://localhost:3000/milestones/511"
    },
    {
      "id": 1512,
      "index": 0,
      "erpid": "20001",
      "guid": "ABCDEF00-1234-4321-ABCD-ABCDEF000512",
      "order": 17,
      "cp": "",
      "cd": "",
      "title": "Milestone QA",
      "delid": "",
      "FY": "2016",
      "mdps": "8/5/2016",
      "mdpf": "9/29/2016",
      "mdas": "8/5/2016",
      "mdaf": "9/25/2016",
      "pcomp": 0,
      "pqty": 0,
      "oqty": 0,
      "units": "Gallons",
      "status": "Finished On-time",
      "rcc": "",
      "rc": "",
      "phase": "",
      "category": "",
      "leadwc": "",
      "comms": "",
      "duration": 26,
      "delete": "N",
      "uri": "http://localhost:3000/milestones/512"
    },
    {
      "id": 1513,
      "index": 2,
      "erpid": "20003",
      "guid": "ABCDEF00-1234-4321-ABCD-ABCDEF000513",
      "order": 4,
      "cp": "",
      "cd": "",
      "title": "Milestone AYY",
      "delid": "",
      "FY": "2016",
      "mdps": "8/5/2016",
      "mdpf": "9/18/2016",
      "mdas": "8/15/2016",
      "mdaf": "9/22/2016",
      "pcomp": 0,
      "pqty": 0,
      "oqty": 0,
      "units": "Gallons",
      "status": "Finished Late",
      "rcc": "",
      "rc": "",
      "phase": "",
      "category": "",
      "leadwc": "",
      "comms": "",
      "duration": 26,
      "delete": "N",
      "uri": "http://localhost:3000/milestones/513"
    },
    {
      "id": 1500,
      "index": 0,
      "erpid": "20001",
      "guid": "ABCDEF00-1234-4321-ABCD-ABCDEF000500",
      "order": 2,
      "cp": "",
      "cd": "",
      "title": "Milestone A",
      "delid": "",
      "FY": "2017",
      "mdps": "10/5/2016",
      "mdpf": "10/31/2016",
      "mdas": "10/4/2016",
      "mdaf": "10/25/2016",
      "pcomp": 0,
      "pqty": 100,
      "oqty": 70,
      "units": "Drums",
      "status": "Finished On-time",
      "rcc": "",
      "rc": "",
      "phase": "",
      "category": "",
      "leadwc": "",
      "duration": 26,
      "comms": "",
      "uri": "http://localhost:3000/milestones/1500"
    },
    {
      "id": 1501,
      "index": 1,
      "erpid": "20001",
      "guid": "ABCDEF00-1234-4321-ABCD-ABCDEF000501",
      "order": 1,
      "cp": "",
      "cd": "",
      "title": "Milestone F",
      "delid": "",
      "FY": "2017",
      "mdps": "11/2/2016",
      "mdpf": "11/28/2016",
      "mdas": "11/5/2016",
      "mdaf": "12/4/2016",
      "pcomp": 0,
      "pqty": 10,
      "oqty": 8,
      "units": "Gallons",
      "status": "Finished Late",
      "rcc": "",
      "rc": "",
      "phase": "",
      "category": "",
      "leadwc": "",
      "duration": 26,
      "comms": "",
      "uri": "http://localhost:3000/milestones/501"
    },
    {
      "id": 1502,
      "index": 3,
      "erpid": "20001",
      "guid": "ABCDEF00-1234-4321-ABCD-ABCDEF000502",
      "order": 5,
      "cp": "",
      "cd": "",
      "title": "Milestone J",
      "delid": "",
      "FY": "2017",
      "mdps": "12/1/2016",
      "mdpf": "12/16/2016",
      "mdas": "11/30/2016",
      "mdaf": "12/6/2016",
      "pcomp": 0,
      "pqty": 200,
      "oqty": 100,
      "units": "Boxes",
      "status": "Finished On-time",
      "rcc": "",
      "rc": "",
      "phase": "",
      "category": "",
      "leadwc": "",
      "duration": 66,
      "comms": "",
      "uri": "http://localhost:3000/milestones/502"
    },
    {
      "id": 1503,
      "index": 2,
      "erpid": "20003",
      "guid": "ABCDEF00-1234-4321-ABCD-ABCDEF000503",
      "order": 4,
      "cp": "",
      "cd": "",
      "title": "Milestone YYA",
      "delid": "",
      "FY": "2017",
      "mdps": "1/5/2017",
      "mdpf": "1/14/2017",
      "mdas": "1/5/2017",
      "mdaf": "3/10/2017",
      "pcomp": 0,
      "pqty": 66,
      "oqty": 56,
      "units": "Gallons",
      "status": "Finished Late",
      "rcc": "",
      "rc": "",
      "phase": "",
      "category": "",
      "leadwc": "",
      "duration": 26,
      "comms": "",
      "uri": "http://localhost:3000/milestones/503"
    },
    {
      "id": 1504,
      "index": 4,
      "erpid": "20003",
      "guid": "ABCDEF00-1234-4321-ABCD-ABCDEF000504",
      "order": 3,
      "cp": "",
      "cd": "",
      "title": "Milestone TT",
      "delid": "",
      "FY": "2017",
      "mdps": "2/5/2017",
      "mdpf": "2/28/2017",
      "mdas": "2/2/2017",
      "mdaf": "2/27/2017",
      "pcomp": 0,
      "pqty": 50,
      "oqty": 25,
      "units": "Units",
      "status": "Finished On-time",
      "rcc": "",
      "rc": "",
      "phase": "",
      "category": "",
      "leadwc": "",
      "duration": 26,
      "comms": "",
      "uri": "http://localhost:3000/milestones/504"
    },
    {
      "id": 1505,
      "index": 0,
      "erpid": "20002",
      "guid": "ABCDEF00-1234-4321-ABCD-ABCDEF000505",
      "order": 17,
      "cp": "",
      "cd": "",
      "title": "Milestone Q",
      "delid": "",
      "FY": "2017",
      "mdps": "2/5/2017",
      "mdpf": "3/31/2017",
      "mdas": "2/5/2017",
      "mdaf": "3/25/2017",
      "pcomp": 0,
      "pqty": 0,
      "oqty": 0,
      "units": "Gallons",
      "status": "Finished On-time",
      "rcc": "",
      "rc": "",
      "phase": "",
      "category": "",
      "leadwc": "",
      "comms": "",
      "duration": 26,
      "delete": "N",
      "uri": "http://localhost:3000/milestones/505"
    },
    {
      "id": 1506,
      "index": 2,
      "erpid": "20001",
      "guid": "ABCDEF00-1234-4321-ABCD-ABCDEF000506",
      "order": 4,
      "cp": "",
      "cd": "",
      "title": "Milestone YY",
      "delid": "",
      "FY": "2017",
      "mdps": "3/5/2017",
      "mdpf": "4/30/2017",
      "mdas": "3/5/2017",
      "mdaf": "5/10/2017",
      "pcomp": 0,
      "pqty": 0,
      "oqty": 0,
      "units": "Gallons",
      "status": "Finished Late",
      "rcc": "",
      "rc": "",
      "phase": "",
      "category": "",
      "leadwc": "",
      "comms": "",
      "duration": 26,
      "delete": "N",
      "uri": "http://localhost:3000/milestones/506"
    },
    {
      "id": 1507,
      "index": 0,
      "erpid": "20002",
      "guid": "ABCDEF00-1234-4321-ABCD-ABCDEF000507",
      "order": 2,
      "cp": "",
      "cd": "",
      "title": "Milestone AA",
      "delid": "",
      "FY": "2017",
      "mdps": "5/5/2017",
      "mdpf": "5/31/2017",
      "mdas": "5/4/2017",
      "mdaf": "5/25/2017",
      "pcomp": 0,
      "pqty": 100,
      "oqty": 70,
      "units": "Drums",
      "status": "Finished On-time",
      "rcc": "",
      "rc": "",
      "phase": "",
      "category": "",
      "leadwc": "",
      "duration": 26,
      "comms": "",
      "uri": "http://localhost:3000/milestones/507"
    },
    {
      "id": 1508,
      "index": 1,
      "erpid": "20002",
      "guid": "ABCDEF00-1234-4321-ABCD-ABCDEF000508",
      "order": 1,
      "cp": "",
      "cd": "",
      "title": "Milestone FA",
      "delid": "",
      "FY": "2017",
      "mdps": "2/2/2017",
      "mdpf": "6/26/2017",
      "mdas": "2/5/2017",
      "mdaf": "7/1/2017",
      "pcomp": 0,
      "pqty": 10,
      "oqty": 8,
      "units": "Gallons",
      "status": "Finished Late",
      "rcc": "",
      "rc": "",
      "phase": "",
      "category": "",
      "leadwc": "",
      "duration": 26,
      "comms": "",
      "uri": "http://localhost:3000/milestones/508"
    },
    {
      "id": 1509,
      "index": 3,
      "erpid": "20001",
      "guid": "ABCDEF00-1234-4321-ABCD-ABCDEF000509",
      "order": 5,
      "cp": "",
      "cd": "",
      "title": "Milestone JA",
      "delid": "",
      "FY": "2017",
      "mdps": "6/1/2017",
      "mdpf": "7/16/2017",
      "mdas": "6/5/2017",
      "mdaf": "7/6/2017",
      "pcomp": 0,
      "pqty": 200,
      "oqty": 100,
      "units": "Boxes",
      "status": "Finished On-time",
      "rcc": "",
      "rc": "",
      "phase": "",
      "category": "",
      "leadwc": "",
      "duration": 66,
      "comms": "",
      "uri": "http://localhost:3000/milestones/509"
    },
    {
      "id": 1510,
      "index": 2,
      "erpid": "20003",
      "guid": "ABCDEF00-1234-4321-ABCD-ABCDEF000510",
      "order": 4,
      "cp": "",
      "cd": "",
      "title": "Milestone YAY",
      "delid": "",
      "FY": "2017",
      "mdps": "6/5/2017",
      "mdpf": "8/14/2017",
      "mdas": "6/5/2017",
      "mdaf": "9/10/2017",
      "pcomp": 0,
      "pqty": 66,
      "oqty": 56,
      "units": "Gallons",
      "status": "Finished Late",
      "rcc": "",
      "rc": "",
      "phase": "",
      "category": "",
      "leadwc": "",
      "duration": 26,
      "comms": "",
      "uri": "http://localhost:3000/milestones/510"
    },
    {
      "id": 1511,
      "index": 4,
      "erpid": "20001",
      "guid": "ABCDEF00-1234-4321-ABCD-ABCDEF000511",
      "order": 3,
      "cp": "",
      "cd": "",
      "title": "Milestone ATAT",
      "delid": "",
      "FY": "2017",
      "mdps": "7/5/2017",
      "mdpf": "8/30/2017",
      "mdas": "5/17/2017",
      "mdaf": "8/7/2017",
      "pcomp": 0,
      "pqty": 50,
      "oqty": 25,
      "units": "Units",
      "status": "Finished On-time",
      "rcc": "",
      "rc": "",
      "phase": "",
      "category": "",
      "leadwc": "",
      "duration": 26,
      "comms": "",
      "uri": "http://localhost:3000/milestones/511"
    },
    {
      "id": 1512,
      "index": 0,
      "erpid": "20001",
      "guid": "ABCDEF00-1234-4321-ABCD-ABCDEF000512",
      "order": 17,
      "cp": "",
      "cd": "",
      "title": "Milestone QA",
      "delid": "",
      "FY": "2017",
      "mdps": "8/5/2017",
      "mdpf": "9/29/2017",
      "mdas": "8/5/2017",
      "mdaf": "9/25/2017",
      "pcomp": 0,
      "pqty": 0,
      "oqty": 0,
      "units": "Gallons",
      "status": "Finished On-time",
      "rcc": "",
      "rc": "",
      "phase": "",
      "category": "",
      "leadwc": "",
      "comms": "",
      "duration": 26,
      "delete": "N",
      "uri": "http://localhost:3000/milestones/512"
    },
    {
      "id": 1513,
      "index": 2,
      "erpid": "20003",
      "guid": "ABCDEF00-1234-4321-ABCD-ABCDEF000513",
      "order": 4,
      "cp": "",
      "cd": "",
      "title": "Milestone AYY",
      "delid": "",
      "FY": "2017",
      "mdps": "8/5/2017",
      "mdpf": "9/18/2017",
      "mdas": "8/15/2017",
      "mdaf": "9/22/2017",
      "pcomp": 0,
      "pqty": 0,
      "oqty": 0,
      "units": "Gallons",
      "status": "Finished Late",
      "rcc": "",
      "rc": "",
      "phase": "",
      "category": "",
      "leadwc": "",
      "comms": "",
      "duration": 26,
      "delete": "N",
      "uri": "http://localhost:3000/milestones/513"
    },
    {
      "id": 1500,
      "index": 0,
      "erpid": "20001",
      "guid": "ABCDEF00-1234-4321-ABCD-ABCDEF000500",
      "order": 2,
      "cp": "",
      "cd": "",
      "title": "Milestone A",
      "delid": "",
      "FY": "2018",
      "mdps": "10/5/2017",
      "mdpf": "10/31/2017",
      "mdas": "10/4/2017",
      "mdaf": "10/25/2017",
      "pcomp": 0,
      "pqty": 100,
      "oqty": 70,
      "units": "Drums",
      "status": "Finished On-time",
      "rcc": "",
      "rc": "",
      "phase": "",
      "category": "",
      "leadwc": "",
      "duration": 26,
      "comms": "",
      "uri": "http://localhost:3000/milestones/1500"
    },
    {
      "id": 1501,
      "index": 1,
      "erpid": "20001",
      "guid": "ABCDEF00-1234-4321-ABCD-ABCDEF000501",
      "order": 1,
      "cp": "",
      "cd": "",
      "title": "Milestone F",
      "delid": "",
      "FY": "2018",
      "mdps": "11/2/2017",
      "mdpf": "11/28/2017",
      "mdas": "11/5/2017",
      "mdaf": "12/4/2017",
      "pcomp": 0,
      "pqty": 10,
      "oqty": 8,
      "units": "Gallons",
      "status": "Finished Late",
      "rcc": "",
      "rc": "",
      "phase": "",
      "category": "",
      "leadwc": "",
      "duration": 26,
      "comms": "",
      "uri": "http://localhost:3000/milestones/501"
    },
    {
      "id": 1502,
      "index": 3,
      "erpid": "20001",
      "guid": "ABCDEF00-1234-4321-ABCD-ABCDEF000502",
      "order": 5,
      "cp": "",
      "cd": "",
      "title": "Milestone J",
      "delid": "",
      "FY": "2018",
      "mdps": "12/1/2017",
      "mdpf": "12/16/2017",
      "mdas": "11/30/2017",
      "mdaf": "12/6/2017",
      "pcomp": 0,
      "pqty": 200,
      "oqty": 100,
      "units": "Boxes",
      "status": "Finished On-time",
      "rcc": "",
      "rc": "",
      "phase": "",
      "category": "",
      "leadwc": "",
      "duration": 66,
      "comms": "",
      "uri": "http://localhost:3000/milestones/502"
    },
    {
      "id": 1503,
      "index": 2,
      "erpid": "20003",
      "guid": "ABCDEF00-1234-4321-ABCD-ABCDEF000503",
      "order": 4,
      "cp": "",
      "cd": "",
      "title": "Milestone YYA",
      "delid": "",
      "FY": "2018",
      "mdps": "1/5/2018",
      "mdpf": "1/14/2018",
      "mdas": "1/5/2018",
      "mdaf": "3/10/2018",
      "pcomp": 0,
      "pqty": 66,
      "oqty": 56,
      "units": "Gallons",
      "status": "Finished Late",
      "rcc": "",
      "rc": "",
      "phase": "",
      "category": "",
      "leadwc": "",
      "duration": 26,
      "comms": "",
      "uri": "http://localhost:3000/milestones/503"
    },
    {
      "id": 1504,
      "index": 4,
      "erpid": "20003",
      "guid": "ABCDEF00-1234-4321-ABCD-ABCDEF000504",
      "order": 3,
      "cp": "",
      "cd": "",
      "title": "Milestone TT",
      "delid": "",
      "FY": "2018",
      "mdps": "2/5/2018",
      "mdpf": "2/28/2018",
      "mdas": "2/2/2018",
      "mdaf": "2/27/2018",
      "pcomp": 0,
      "pqty": 50,
      "oqty": 25,
      "units": "Units",
      "status": "Finished On-time",
      "rcc": "",
      "rc": "",
      "phase": "",
      "category": "",
      "leadwc": "",
      "duration": 26,
      "comms": "",
      "uri": "http://localhost:3000/milestones/504"
    },
    {
      "id": 1505,
      "index": 0,
      "erpid": "20002",
      "guid": "ABCDEF00-1234-4321-ABCD-ABCDEF000505",
      "order": 17,
      "cp": "",
      "cd": "",
      "title": "Milestone Q",
      "delid": "",
      "FY": "2018",
      "mdps": "2/5/2018",
      "mdpf": "3/31/2018",
      "mdas": "2/5/2018",
      "mdaf": "3/25/2018",
      "pcomp": 0,
      "pqty": 0,
      "oqty": 0,
      "units": "Gallons",
      "status": "Finished On-time",
      "rcc": "",
      "rc": "",
      "phase": "",
      "category": "",
      "leadwc": "",
      "comms": "",
      "duration": 26,
      "delete": "N",
      "uri": "http://localhost:3000/milestones/505"
    },
    {
      "id": 1506,
      "index": 2,
      "erpid": "20001",
      "guid": "ABCDEF00-1234-4321-ABCD-ABCDEF000506",
      "order": 4,
      "cp": "",
      "cd": "",
      "title": "Milestone YY",
      "delid": "",
      "FY": "2018",
      "mdps": "3/5/2018",
      "mdpf": "4/30/2018",
      "mdas": "3/5/2018",
      "mdaf": "5/10/2018",
      "pcomp": 0,
      "pqty": 0,
      "oqty": 0,
      "units": "Gallons",
      "status": "Finished Late",
      "rcc": "",
      "rc": "",
      "phase": "",
      "category": "",
      "leadwc": "",
      "comms": "",
      "duration": 26,
      "delete": "N",
      "uri": "http://localhost:3000/milestones/506"
    },
    {
      "id": 1507,
      "index": 0,
      "erpid": "20002",
      "guid": "ABCDEF00-1234-4321-ABCD-ABCDEF000507",
      "order": 2,
      "cp": "",
      "cd": "",
      "title": "Milestone AA",
      "delid": "",
      "FY": "2018",
      "mdps": "5/5/2018",
      "mdpf": "5/31/2018",
      "mdas": "5/4/2018",
      "mdaf": "5/25/2018",
      "pcomp": 0,
      "pqty": 100,
      "oqty": 70,
      "units": "Drums",
      "status": "Finished On-time",
      "rcc": "",
      "rc": "",
      "phase": "",
      "category": "",
      "leadwc": "",
      "duration": 26,
      "comms": "",
      "uri": "http://localhost:3000/milestones/507"
    },
    {
      "id": 1508,
      "index": 1,
      "erpid": "20002",
      "guid": "ABCDEF00-1234-4321-ABCD-ABCDEF000508",
      "order": 1,
      "cp": "",
      "cd": "",
      "title": "Milestone FA",
      "delid": "",
      "FY": "2018",
      "mdps": "2/2/2018",
      "mdpf": "6/26/2018",
      "mdas": "2/5/2018",
      "mdaf": "7/1/2018",
      "pcomp": 0,
      "pqty": 10,
      "oqty": 8,
      "units": "Gallons",
      "status": "Finished Late",
      "rcc": "",
      "rc": "",
      "phase": "",
      "category": "",
      "leadwc": "",
      "duration": 26,
      "comms": "",
      "uri": "http://localhost:3000/milestones/508"
    },
    {
      "id": 1509,
      "index": 3,
      "erpid": "20001",
      "guid": "ABCDEF00-1234-4321-ABCD-ABCDEF000509",
      "order": 5,
      "cp": "",
      "cd": "",
      "title": "Milestone JA",
      "delid": "",
      "FY": "2018",
      "mdps": "6/1/2018",
      "mdpf": "7/16/2018",
      "mdas": "6/5/2018",
      "mdaf": "7/6/2018",
      "pcomp": 0,
      "pqty": 200,
      "oqty": 100,
      "units": "Boxes",
      "status": "Finished On-time",
      "rcc": "",
      "rc": "",
      "phase": "",
      "category": "",
      "leadwc": "",
      "duration": 66,
      "comms": "",
      "uri": "http://localhost:3000/milestones/509"
    },
    {
      "id": 1510,
      "index": 2,
      "erpid": "20003",
      "guid": "ABCDEF00-1234-4321-ABCD-ABCDEF000510",
      "order": 4,
      "cp": "",
      "cd": "",
      "title": "Milestone YAY",
      "delid": "",
      "FY": "2018",
      "mdps": "6/5/2018",
      "mdpf": "8/14/2018",
      "mdas": "6/5/2018",
      "mdaf": "9/10/2018",
      "pcomp": 0,
      "pqty": 66,
      "oqty": 56,
      "units": "Gallons",
      "status": "Finished Late",
      "rcc": "",
      "rc": "",
      "phase": "",
      "category": "",
      "leadwc": "",
      "duration": 26,
      "comms": "",
      "uri": "http://localhost:3000/milestones/510"
    },
    {
      "id": 1511,
      "index": 4,
      "erpid": "20001",
      "guid": "ABCDEF00-1234-4321-ABCD-ABCDEF000511",
      "order": 3,
      "cp": "",
      "cd": "",
      "title": "Milestone ATAT",
      "delid": "",
      "FY": "2018",
      "mdps": "7/5/2018",
      "mdpf": "8/30/2018",
      "mdas": "5/17/2018",
      "mdaf": "8/7/2018",
      "pcomp": 0,
      "pqty": 50,
      "oqty": 25,
      "units": "Units",
      "status": "Finished On-time",
      "rcc": "",
      "rc": "",
      "phase": "",
      "category": "",
      "leadwc": "",
      "duration": 26,
      "comms": "",
      "uri": "http://localhost:3000/milestones/511"
    },
    {
      "id": 1512,
      "index": 0,
      "erpid": "20001",
      "guid": "ABCDEF00-1234-4321-ABCD-ABCDEF000512",
      "order": 17,
      "cp": "",
      "cd": "",
      "title": "Milestone QA",
      "delid": "",
      "FY": "2018",
      "mdps": "8/5/2018",
      "mdpf": "9/29/2018",
      "mdas": "8/5/2018",
      "mdaf": "9/25/2018",
      "pcomp": 0,
      "pqty": 0,
      "oqty": 0,
      "units": "Gallons",
      "status": "Finished On-time",
      "rcc": "",
      "rc": "",
      "phase": "",
      "category": "",
      "leadwc": "",
      "comms": "",
      "duration": 26,
      "delete": "N",
      "uri": "http://localhost:3000/milestones/512"
    },
    {
      "id": 1513,
      "index": 2,
      "erpid": "20003",
      "guid": "ABCDEF00-1234-4321-ABCD-ABCDEF000513",
      "order": 4,
      "cp": "",
      "cd": "",
      "title": "Milestone AYY",
      "delid": "",
      "FY": "2018",
      "mdps": "8/5/2018",
      "mdpf": "9/18/2018",
      "mdas": "8/15/2018",
      "mdaf": "9/22/2018",
      "pcomp": 0,
      "pqty": 0,
      "oqty": 0,
      "units": "Gallons",
      "status": "Finished Late",
      "rcc": "",
      "rc": "",
      "phase": "",
      "category": "",
      "leadwc": "",
      "comms": "",
      "duration": 26,
      "delete": "N",
      "uri": "http://localhost:3000/milestones/513"
    },
    {
      "id": 1500,
      "index": 0,
      "erpid": "20001",
      "guid": "ABCDEF00-1234-4321-ABCD-ABCDEF000500",
      "order": 2,
      "cp": "",
      "cd": "",
      "title": "Milestone A",
      "delid": "",
      "FY": "2019",
      "mdps": "10/5/2018",
      "mdpf": "10/31/2018",
      "mdas": "10/4/2018",
      "mdaf": "10/25/2018",
      "pcomp": 0,
      "pqty": 100,
      "oqty": 70,
      "units": "Drums",
      "status": "Finished On-time",
      "rcc": "",
      "rc": "",
      "phase": "",
      "category": "",
      "leadwc": "",
      "duration": 26,
      "comms": "",
      "uri": "http://localhost:3000/milestones/1500"
    },
    {
      "id": 1501,
      "index": 1,
      "erpid": "20001",
      "guid": "ABCDEF00-1234-4321-ABCD-ABCDEF000501",
      "order": 1,
      "cp": "",
      "cd": "",
      "title": "Milestone F",
      "delid": "",
      "FY": "2019",
      "mdps": "11/2/2018",
      "mdpf": "11/28/2018",
      "mdas": "11/5/2018",
      "mdaf": "12/4/2018",
      "pcomp": 0,
      "pqty": 10,
      "oqty": 8,
      "units": "Gallons",
      "status": "Finished Late",
      "rcc": "",
      "rc": "",
      "phase": "",
      "category": "",
      "leadwc": "",
      "duration": 26,
      "comms": "",
      "uri": "http://localhost:3000/milestones/501"
    },
    {
      "id": 1502,
      "index": 3,
      "erpid": "20001",
      "guid": "ABCDEF00-1234-4321-ABCD-ABCDEF000502",
      "order": 5,
      "cp": "",
      "cd": "",
      "title": "Milestone J",
      "delid": "",
      "FY": "2019",
      "mdps": "12/1/2018",
      "mdpf": "12/16/2018",
      "mdas": "11/30/2018",
      "mdaf": "12/6/2018",
      "pcomp": 0,
      "pqty": 200,
      "oqty": 100,
      "units": "Boxes",
      "status": "Finished On-time",
      "rcc": "",
      "rc": "",
      "phase": "",
      "category": "",
      "leadwc": "",
      "duration": 66,
      "comms": "",
      "uri": "http://localhost:3000/milestones/502"
    },
    {
      "id": 1503,
      "index": 2,
      "erpid": "20003",
      "guid": "ABCDEF00-1234-4321-ABCD-ABCDEF000503",
      "order": 4,
      "cp": "",
      "cd": "",
      "title": "Milestone YYA",
      "delid": "",
      "FY": "2019",
      "mdps": "1/5/2019",
      "mdpf": "1/14/2019",
      "mdas": "1/5/2019",
      "mdaf": "3/10/2019",
      "pcomp": 0,
      "pqty": 66,
      "oqty": 56,
      "units": "Gallons",
      "status": "Finished Late",
      "rcc": "",
      "rc": "",
      "phase": "",
      "category": "",
      "leadwc": "",
      "duration": 26,
      "comms": "",
      "uri": "http://localhost:3000/milestones/503"
    },
    {
      "id": 1504,
      "index": 4,
      "erpid": "20003",
      "guid": "ABCDEF00-1234-4321-ABCD-ABCDEF000504",
      "order": 3,
      "cp": "",
      "cd": "",
      "title": "Milestone TT",
      "delid": "",
      "FY": "2019",
      "mdps": "2/5/2019",
      "mdpf": "2/28/2019",
      "mdas": "2/2/2019",
      "mdaf": "2/27/2019",
      "pcomp": 0,
      "pqty": 50,
      "oqty": 25,
      "units": "Units",
      "status": "Finished On-time",
      "rcc": "",
      "rc": "",
      "phase": "",
      "category": "",
      "leadwc": "",
      "duration": 26,
      "comms": "",
      "uri": "http://localhost:3000/milestones/504"
    },
    {
      "id": 1505,
      "index": 0,
      "erpid": "20002",
      "guid": "ABCDEF00-1234-4321-ABCD-ABCDEF000505",
      "order": 17,
      "cp": "",
      "cd": "",
      "title": "Milestone Q",
      "delid": "",
      "FY": "2019",
      "mdps": "2/5/2019",
      "mdpf": "3/31/2019",
      "mdas": "2/5/2019",
      "mdaf": "3/25/2019",
      "pcomp": 0,
      "pqty": 0,
      "oqty": 0,
      "units": "Gallons",
      "status": "Finished On-time",
      "rcc": "",
      "rc": "",
      "phase": "",
      "category": "",
      "leadwc": "",
      "comms": "",
      "duration": 26,
      "delete": "N",
      "uri": "http://localhost:3000/milestones/505"
    },
    {
      "id": 1506,
      "index": 2,
      "erpid": "20001",
      "guid": "ABCDEF00-1234-4321-ABCD-ABCDEF000506",
      "order": 4,
      "cp": "",
      "cd": "",
      "title": "Milestone YY",
      "delid": "",
      "FY": "2019",
      "mdps": "3/5/2019",
      "mdpf": "4/30/2019",
      "mdas": "3/5/2019",
      "mdaf": "5/10/2019",
      "pcomp": 0,
      "pqty": 0,
      "oqty": 0,
      "units": "Gallons",
      "status": "Finished Late",
      "rcc": "",
      "rc": "",
      "phase": "",
      "category": "",
      "leadwc": "",
      "comms": "",
      "duration": 26,
      "delete": "N",
      "uri": "http://localhost:3000/milestones/506"
    },
    {
      "id": 1507,
      "index": 0,
      "erpid": "20002",
      "guid": "ABCDEF00-1234-4321-ABCD-ABCDEF000507",
      "order": 2,
      "cp": "",
      "cd": "",
      "title": "Milestone AA",
      "delid": "",
      "FY": "2019",
      "mdps": "5/5/2019",
      "mdpf": "5/31/2019",
      "mdas": "5/4/2019",
      "mdaf": "5/25/2019",
      "pcomp": 0,
      "pqty": 100,
      "oqty": 70,
      "units": "Drums",
      "status": "Finished On-time",
      "rcc": "",
      "rc": "",
      "phase": "",
      "category": "",
      "leadwc": "",
      "duration": 26,
      "comms": "",
      "uri": "http://localhost:3000/milestones/507"
    },
    {
      "id": 1508,
      "index": 1,
      "erpid": "20002",
      "guid": "ABCDEF00-1234-4321-ABCD-ABCDEF000508",
      "order": 1,
      "cp": "",
      "cd": "",
      "title": "Milestone FA",
      "delid": "",
      "FY": "2019",
      "mdps": "2/2/2019",
      "mdpf": "6/26/2019",
      "mdas": "2/5/2019",
      "mdaf": "7/1/2019",
      "pcomp": 0,
      "pqty": 10,
      "oqty": 8,
      "units": "Gallons",
      "status": "Finished Late",
      "rcc": "",
      "rc": "",
      "phase": "",
      "category": "",
      "leadwc": "",
      "duration": 26,
      "comms": "",
      "uri": "http://localhost:3000/milestones/508"
    },
    {
      "id": 1509,
      "index": 3,
      "erpid": "20001",
      "guid": "ABCDEF00-1234-4321-ABCD-ABCDEF000509",
      "order": 5,
      "cp": "",
      "cd": "",
      "title": "Milestone JA",
      "delid": "",
      "FY": "2019",
      "mdps": "6/1/2019",
      "mdpf": "7/16/2019",
      "mdas": "6/5/2019",
      "mdaf": "7/6/2019",
      "pcomp": 0,
      "pqty": 200,
      "oqty": 100,
      "units": "Boxes",
      "status": "Finished On-time",
      "rcc": "",
      "rc": "",
      "phase": "",
      "category": "",
      "leadwc": "",
      "duration": 66,
      "comms": "",
      "uri": "http://localhost:3000/milestones/509"
    },
    {
      "id": 1510,
      "index": 2,
      "erpid": "20003",
      "guid": "ABCDEF00-1234-4321-ABCD-ABCDEF000510",
      "order": 4,
      "cp": "",
      "cd": "",
      "title": "Milestone YAY",
      "delid": "",
      "FY": "2019",
      "mdps": "6/5/2019",
      "mdpf": "8/14/2019",
      "mdas": "6/5/2019",
      "mdaf": "9/10/2019",
      "pcomp": 0,
      "pqty": 66,
      "oqty": 56,
      "units": "Gallons",
      "status": "Finished Late",
      "rcc": "",
      "rc": "",
      "phase": "",
      "category": "",
      "leadwc": "",
      "duration": 26,
      "comms": "",
      "uri": "http://localhost:3000/milestones/510"
    },
    {
      "id": 1511,
      "index": 4,
      "erpid": "20001",
      "guid": "ABCDEF00-1234-4321-ABCD-ABCDEF000511",
      "order": 3,
      "cp": "",
      "cd": "",
      "title": "Milestone ATAT",
      "delid": "",
      "FY": "2019",
      "mdps": "7/5/2019",
      "mdpf": "8/30/2019",
      "mdas": "5/17/2019",
      "mdaf": "8/7/2019",
      "pcomp": 0,
      "pqty": 50,
      "oqty": 25,
      "units": "Units",
      "status": "Finished On-time",
      "rcc": "",
      "rc": "",
      "phase": "",
      "category": "",
      "leadwc": "",
      "duration": 26,
      "comms": "",
      "uri": "http://localhost:3000/milestones/511"
    },
    {
      "id": 1512,
      "index": 0,
      "erpid": "20001",
      "guid": "ABCDEF00-1234-4321-ABCD-ABCDEF000512",
      "order": 17,
      "cp": "",
      "cd": "",
      "title": "Milestone QA",
      "delid": "",
      "FY": "2019",
      "mdps": "8/5/2019",
      "mdpf": "9/29/2019",
      "mdas": "8/5/2019",
      "mdaf": "9/25/2019",
      "pcomp": 0,
      "pqty": 0,
      "oqty": 0,
      "units": "Gallons",
      "status": "Finished On-time",
      "rcc": "",
      "rc": "",
      "phase": "",
      "category": "",
      "leadwc": "",
      "comms": "",
      "duration": 26,
      "delete": "N",
      "uri": "http://localhost:3000/milestones/512"
    },
    {
      "id": 1513,
      "index": 2,
      "erpid": "20003",
      "guid": "ABCDEF00-1234-4321-ABCD-ABCDEF000513",
      "order": 4,
      "cp": "",
      "cd": "",
      "title": "Milestone AYY",
      "delid": "",
      "FY": "2019",
      "mdps": "8/5/2019",
      "mdpf": "9/18/2019",
      "mdas": "8/15/2019",
      "mdaf": "9/22/2019",
      "pcomp": 0,
      "pqty": 0,
      "oqty": 0,
      "units": "Gallons",
      "status": "Finished Late",
      "rcc": "",
      "rc": "",
      "phase": "",
      "category": "",
      "leadwc": "",
      "comms": "",
      "duration": 26,
      "delete": "N",
      "uri": "http://localhost:3000/milestones/513"
    },
    {
      "id": 1500,
      "index": 0,
      "erpid": "20001",
      "guid": "ABCDEF00-1234-4321-ABCD-ABCDEF000500",
      "order": 2,
      "cp": "",
      "cd": "",
      "title": "Milestone A",
      "delid": "",
      "FY": "2020",
      "mdps": "10/5/2019",
      "mdpf": "10/31/2019",
      "mdas": "10/4/2019",
      "mdaf": "10/25/2019",
      "pcomp": 0,
      "pqty": 100,
      "oqty": 70,
      "units": "Drums",
      "status": "Finished On-time",
      "rcc": "",
      "rc": "",
      "phase": "",
      "category": "",
      "leadwc": "",
      "duration": 26,
      "comms": "",
      "uri": "http://localhost:3000/milestones/1500"
    },
    {
      "id": 1501,
      "index": 1,
      "erpid": "20001",
      "guid": "ABCDEF00-1234-4321-ABCD-ABCDEF000501",
      "order": 1,
      "cp": "",
      "cd": "",
      "title": "Milestone F",
      "delid": "",
      "FY": "2020",
      "mdps": "11/2/2019",
      "mdpf": "11/28/2019",
      "mdas": "11/5/2019",
      "mdaf": "12/4/2019",
      "pcomp": 0,
      "pqty": 10,
      "oqty": 8,
      "units": "Gallons",
      "status": "Finished Late",
      "rcc": "",
      "rc": "",
      "phase": "",
      "category": "",
      "leadwc": "",
      "duration": 26,
      "comms": "",
      "uri": "http://localhost:3000/milestones/501"
    },
    {
      "id": 1502,
      "index": 3,
      "erpid": "20001",
      "guid": "ABCDEF00-1234-4321-ABCD-ABCDEF000502",
      "order": 5,
      "cp": "",
      "cd": "",
      "title": "Milestone J",
      "delid": "",
      "FY": "2020",
      "mdps": "12/1/2019",
      "mdpf": "12/16/2019",
      "mdas": "11/30/2019",
      "mdaf": "12/6/2019",
      "pcomp": 0,
      "pqty": 200,
      "oqty": 100,
      "units": "Boxes",
      "status": "Finished On-time",
      "rcc": "",
      "rc": "",
      "phase": "",
      "category": "",
      "leadwc": "",
      "duration": 66,
      "comms": "",
      "uri": "http://localhost:3000/milestones/502"
    },
    {
      "id": 1503,
      "index": 2,
      "erpid": "20003",
      "guid": "ABCDEF00-1234-4321-ABCD-ABCDEF000503",
      "order": 4,
      "cp": "",
      "cd": "",
      "title": "Milestone YYA",
      "delid": "",
      "FY": "2020",
      "mdps": "1/5/2020",
      "mdpf": "1/14/2020",
      "mdas": "1/5/2020",
      "mdaf": "3/10/2020",
      "pcomp": 0,
      "pqty": 66,
      "oqty": 56,
      "units": "Gallons",
      "status": "Finished Late",
      "rcc": "",
      "rc": "",
      "phase": "",
      "category": "",
      "leadwc": "",
      "duration": 26,
      "comms": "",
      "uri": "http://localhost:3000/milestones/503"
    },
    {
      "id": 1504,
      "index": 4,
      "erpid": "20003",
      "guid": "ABCDEF00-1234-4321-ABCD-ABCDEF000504",
      "order": 3,
      "cp": "",
      "cd": "",
      "title": "Milestone TT",
      "delid": "",
      "FY": "2020",
      "mdps": "2/5/2020",
      "mdpf": "2/28/2020",
      "mdas": "2/2/2020",
      "mdaf": "2/27/2020",
      "pcomp": 0,
      "pqty": 50,
      "oqty": 25,
      "units": "Units",
      "status": "Finished On-time",
      "rcc": "",
      "rc": "",
      "phase": "",
      "category": "",
      "leadwc": "",
      "duration": 26,
      "comms": "",
      "uri": "http://localhost:3000/milestones/504"
    },
    {
      "id": 1505,
      "index": 0,
      "erpid": "20002",
      "guid": "ABCDEF00-1234-4321-ABCD-ABCDEF000505",
      "order": 17,
      "cp": "",
      "cd": "",
      "title": "Milestone Q",
      "delid": "",
      "FY": "2020",
      "mdps": "2/5/2020",
      "mdpf": "3/31/2020",
      "mdas": "2/5/2020",
      "mdaf": "3/25/2020",
      "pcomp": 0,
      "pqty": 0,
      "oqty": 0,
      "units": "Gallons",
      "status": "Finished On-time",
      "rcc": "",
      "rc": "",
      "phase": "",
      "category": "",
      "leadwc": "",
      "comms": "",
      "duration": 26,
      "delete": "N",
      "uri": "http://localhost:3000/milestones/505"
    },
    {
      "id": 1506,
      "index": 2,
      "erpid": "20001",
      "guid": "ABCDEF00-1234-4321-ABCD-ABCDEF000506",
      "order": 4,
      "cp": "",
      "cd": "",
      "title": "Milestone YY",
      "delid": "",
      "FY": "2020",
      "mdps": "3/5/2020",
      "mdpf": "4/30/2020",
      "mdas": "3/5/2020",
      "mdaf": "5/10/2020",
      "pcomp": 0,
      "pqty": 0,
      "oqty": 0,
      "units": "Gallons",
      "status": "Finished Late",
      "rcc": "",
      "rc": "",
      "phase": "",
      "category": "",
      "leadwc": "",
      "comms": "",
      "duration": 26,
      "delete": "N",
      "uri": "http://localhost:3000/milestones/506"
    },
    {
      "id": 1507,
      "index": 0,
      "erpid": "20002",
      "guid": "ABCDEF00-1234-4321-ABCD-ABCDEF000507",
      "order": 2,
      "cp": "",
      "cd": "",
      "title": "Milestone AA",
      "delid": "",
      "FY": "2020",
      "mdps": "5/5/2020",
      "mdpf": "5/31/2020",
      "mdas": "5/4/2020",
      "mdaf": "5/25/2020",
      "pcomp": 0,
      "pqty": 100,
      "oqty": 70,
      "units": "Drums",
      "status": "Finished On-time",
      "rcc": "",
      "rc": "",
      "phase": "",
      "category": "",
      "leadwc": "",
      "duration": 26,
      "comms": "",
      "uri": "http://localhost:3000/milestones/507"
    },
    {
      "id": 1508,
      "index": 1,
      "erpid": "20002",
      "guid": "ABCDEF00-1234-4321-ABCD-ABCDEF000508",
      "order": 1,
      "cp": "",
      "cd": "",
      "title": "Milestone FA",
      "delid": "",
      "FY": "2020",
      "mdps": "2/2/2020",
      "mdpf": "6/26/2020",
      "mdas": "2/5/2020",
      "mdaf": "7/1/2020",
      "pcomp": 0,
      "pqty": 10,
      "oqty": 8,
      "units": "Gallons",
      "status": "Finished Late",
      "rcc": "",
      "rc": "",
      "phase": "",
      "category": "",
      "leadwc": "",
      "duration": 26,
      "comms": "",
      "uri": "http://localhost:3000/milestones/508"
    },
    {
      "id": 1509,
      "index": 3,
      "erpid": "20001",
      "guid": "ABCDEF00-1234-4321-ABCD-ABCDEF000509",
      "order": 5,
      "cp": "",
      "cd": "",
      "title": "Milestone JA",
      "delid": "",
      "FY": "2020",
      "mdps": "6/1/2020",
      "mdpf": "7/16/2020",
      "mdas": "6/5/2020",
      "mdaf": "7/6/2020",
      "pcomp": 0,
      "pqty": 200,
      "oqty": 100,
      "units": "Boxes",
      "status": "Finished On-time",
      "rcc": "",
      "rc": "",
      "phase": "",
      "category": "",
      "leadwc": "",
      "duration": 66,
      "comms": "",
      "uri": "http://localhost:3000/milestones/509"
    },
    {
      "id": 1510,
      "index": 2,
      "erpid": "20003",
      "guid": "ABCDEF00-1234-4321-ABCD-ABCDEF000510",
      "order": 4,
      "cp": "",
      "cd": "",
      "title": "Milestone YAY",
      "delid": "",
      "FY": "2020",
      "mdps": "6/5/2020",
      "mdpf": "8/14/2020",
      "mdas": "6/5/2020",
      "mdaf": "9/10/2020",
      "pcomp": 0,
      "pqty": 66,
      "oqty": 56,
      "units": "Gallons",
      "status": "Finished Late",
      "rcc": "",
      "rc": "",
      "phase": "",
      "category": "",
      "leadwc": "",
      "duration": 26,
      "comms": "",
      "uri": "http://localhost:3000/milestones/510"
    },
    {
      "id": 1511,
      "index": 4,
      "erpid": "ZEBRA",
      "guid": "ABCDEF00-1234-4321-ABCD-ABCDEF000511",
      "order": 3,
      "cp": "",
      "cd": "",
      "title": "Milestone ATAT",
      "delid": "",
      "FY": "2020",
      "mdps": "7/5/2020",
      "mdpf": "8/30/2020",
      "mdas": "5/17/2020",
      "mdaf": "8/7/2020",
      "pcomp": 0,
      "pqty": 50,
      "oqty": 25,
      "units": "Units",
      "status": "Finished On-time",
      "rcc": "",
      "rc": "",
      "phase": "",
      "category": "",
      "leadwc": "",
      "duration": 26,
      "comms": "",
      "uri": "http://localhost:3000/milestones/511"
    },
    {
      "id": 1512,
      "index": 0,
      "erpid": "20001",
      "guid": "ABCDEF00-1234-4321-ABCD-ABCDEF000512",
      "order": 17,
      "cp": "",
      "cd": "",
      "title": "Milestone QA",
      "delid": "",
      "FY": "2020",
      "mdps": "8/5/2020",
      "mdpf": "9/29/2020",
      "mdas": "8/5/2020",
      "mdaf": "9/25/2020",
      "pcomp": 0,
      "pqty": 0,
      "oqty": 0,
      "units": "Gallons",
      "status": "Finished On-time",
      "rcc": "",
      "rc": "",
      "phase": "",
      "category": "",
      "leadwc": "",
      "comms": "",
      "duration": 26,
      "delete": "N",
      "uri": "http://localhost:3000/milestones/512"
    },
    {
      "id": 1513,
      "index": 2,
      "erpid": "20003",
      "guid": "ABCDEF00-1234-4321-ABCD-ABCDEF000513",
      "order": 4,
      "cp": "",
      "cd": "",
      "title": "Milestone AYY",
      "delid": "",
      "FY": "2020",
      "mdps": "8/5/2020",
      "mdpf": "9/18/2020",
      "mdas": "8/15/2020",
      "mdaf": "9/22/2020",
      "pcomp": 0,
      "pqty": 0,
      "oqty": 0,
      "units": "Gallons",
      "status": "Finished Late",
      "rcc": "",
      "rc": "",
      "phase": "",
      "category": "",
      "leadwc": "",
      "comms": "",
      "duration": 26,
      "delete": "N",
      "uri": "http://localhost:3000/milestones/513"
    }
  ]
}
